<?xml version="1.0" encoding="utf-8"?><AvailabilitySearchResult xmlns:xsd="http://www.w3.org/2001/XMLSchema" xmlns:xsi="http://www.w3.org/2001/XMLSchema-instance"><Currency>GBP</Currency><Warning>
</Warning><TestMode>true</TestMode><HotelAvailability><Hotel id="147355" name="Regent Berlin" type="Hotel" stars="5" rank="1"><Region id="20616" name="Mitte" /><Address><Address1>Charlottenstrasse 49</Address1><City>Berlin</City><Zip>10117</Zip><Country>Germany</Country><Tel>0049 (0)3020338</Tel><Fax>0049 (0)3020336119</Fax><Email>reservation.berlin@rezidorregent.com</Email></Address><GeneralInfo /><Photo><Url>http://www.roomsxmldemo.com/RXLStagingImages/1013/hotel14834-Regent-front_Thumbnailed.jpg</Url><Width>70</Width><Height>70</Height><Bytes>2656</Bytes><ThumbnailUrl>http://www.roomsxmldemo.com/RXLStagingImages/1013/hotel14834-Regent-front_Thumbnailed.thumb.jpg</ThumbnailUrl><ThumbnailWidth>70</ThumbnailWidth><ThumbnailHeight>70</ThumbnailHeight><ThumbnailBytes>2655</ThumbnailBytes><PhotoType>ExternalViewOfTheHotel</PhotoType></Photo><Photo><Url>http://www.roomsxmldemo.com/RXLStagingImages/1013/hotel14834-Regent-front.jpg</Url><Width>200</Width><Height>200</Height><Bytes>15307</Bytes><ThumbnailUrl>http://www.roomsxmldemo.com/RXLStagingImages/1013/hotel14834-Regent-front.thumb.jpg</ThumbnailUrl><ThumbnailWidth>70</ThumbnailWidth><ThumbnailHeight>70</ThumbnailHeight><ThumbnailBytes>2273</ThumbnailBytes><PhotoType>ExternalViewOfTheHotel</PhotoType></Photo><Photo><Url>http://www.roomsxmldemo.com/RXLStagingImages/1013/hotel14834-Regent-room.jpg</Url><Width>200</Width><Height>200</Height><Bytes>15845</Bytes><ThumbnailUrl>http://www.roomsxmldemo.com/RXLStagingImages/1013/hotel14834-Regent-room.thumb.jpg</ThumbnailUrl><ThumbnailWidth>70</ThumbnailWidth><ThumbnailHeight>70</ThumbnailHeight><ThumbnailBytes>2005</ThumbnailBytes><PhotoType>ViewOfAGuestRoom</PhotoType></Photo><Photo><Url>http://www.roomsxmldemo.com/RXLStagingImages/1013/hotel14834-Regent-room2.jpg</Url><Width>200</Width><Height>200</Height><Bytes>13445</Bytes><ThumbnailUrl>http://www.roomsxmldemo.com/RXLStagingImages/1013/hotel14834-Regent-room2.thumb.jpg</ThumbnailUrl><ThumbnailWidth>70</ThumbnailWidth><ThumbnailHeight>70</ThumbnailHeight><ThumbnailBytes>1768</ThumbnailBytes><PhotoType>ViewOfAGuestRoom</PhotoType></Photo><Photo><Url>http://www.roomsxmldemo.com/RXLStagingImages/1013/hotel14834-Regent-lounge.jpg</Url><Width>200</Width><Height>200</Height><Bytes>15270</Bytes><ThumbnailUrl>http://www.roomsxmldemo.com/RXLStagingImages/1013/hotel14834-Regent-lounge.thumb.jpg</ThumbnailUrl><ThumbnailWidth>70</ThumbnailWidth><ThumbnailHeight>70</ThumbnailHeight><ThumbnailBytes>2308</ThumbnailBytes><PhotoType>LobbyRestaurantAndBar</PhotoType></Photo><Photo><Url>http://www.roomsxmldemo.com/RXLStagingImages/1013/hotel14834-Regent-lobby.jpg</Url><Width>200</Width><Height>200</Height><Bytes>14918</Bytes><ThumbnailUrl>http://www.roomsxmldemo.com/RXLStagingImages/1013/hotel14834-Regent-lobby.thumb.jpg</ThumbnailUrl><ThumbnailWidth>70</ThumbnailWidth><ThumbnailHeight>70</ThumbnailHeight><ThumbnailBytes>2215</ThumbnailBytes><PhotoType>LobbyRestaurantAndBar</PhotoType></Photo><Photo><Url>http://www.roomsxmldemo.com/RXLStagingImages/1013/hotel14834-Regent-dining.jpg</Url><Width>200</Width><Height>200</Height><Bytes>15725</Bytes><ThumbnailUrl>http://www.roomsxmldemo.com/RXLStagingImages/1013/hotel14834-Regent-dining.thumb.jpg</ThumbnailUrl><ThumbnailWidth>70</ThumbnailWidth><ThumbnailHeight>70</ThumbnailHeight><ThumbnailBytes>2363</ThumbnailBytes><PhotoType>LobbyRestaurantAndBar</PhotoType></Photo><Photo><Url>http://www.roomsxmldemo.com/RXLStagingImages/1013/hotel14834-Regent-meeting.jpg</Url><Width>200</Width><Height>200</Height><Bytes>14550</Bytes><ThumbnailUrl>http://www.roomsxmldemo.com/RXLStagingImages/1013/hotel14834-Regent-meeting.thumb.jpg</ThumbnailUrl><ThumbnailWidth>70</ThumbnailWidth><ThumbnailHeight>70</ThumbnailHeight><ThumbnailBytes>2160</ThumbnailBytes><PhotoType>HotelAmenities</PhotoType></Photo><Photo><Url>http://www.roomsxmldemo.com/RXLStagingImages/1013/hotel14834-Regent-relax.jpg</Url><Width>200</Width><Height>200</Height><Bytes>14430</Bytes><ThumbnailUrl>http://www.roomsxmldemo.com/RXLStagingImages/1013/hotel14834-Regent-relax.thumb.jpg</ThumbnailUrl><ThumbnailWidth>70</ThumbnailWidth><ThumbnailHeight>70</ThumbnailHeight><ThumbnailBytes>2334</ThumbnailBytes><PhotoType>OtherPhotos</PhotoType></Photo><Photo><Url>http://www.roomsxmldemo.com/RXLStagingImages/1013/hotel14834-Regent-bed.jpg</Url><Width>200</Width><Height>200</Height><Bytes>15797</Bytes><ThumbnailUrl>http://www.roomsxmldemo.com/RXLStagingImages/1013/hotel14834-Regent-bed.thumb.jpg</ThumbnailUrl><ThumbnailWidth>70</ThumbnailWidth><ThumbnailHeight>70</ThumbnailHeight><ThumbnailBytes>1772</ThumbnailBytes><PhotoType>OtherPhotos</PhotoType></Photo><Description><Language>en</Language><Type>SurroundingArea</Type><Text>This exclusive city hotel is located opposite the Gendarmenmarkt square in the Mitte district of Berlin just a few minutes walk from the Brandenburg Gate. Nearby Friedrichstraße counts amongst the most exclusive shopping streets in the metropolis and its many restaurants mean that it is a true paradise for gourmets. Links to the public transport network may easily be reached on foot.</Text></Description><Description><Language>en</Language><Type>RoomTypes</Type><Text>Each of the rooms is appointed with air conditioning, a kitchen and a bathroom. The basic features of most rooms include a balcony. A safe and a minibar are also available. A fridge, a mini fridge and a tea/coffee station ensure a comfortable stay. Internet access, a telephone, a TV, a CD player, a DVD player and WiFi add to the comfort of the holiday. Guests will also find slippers in their rooms. The bathrooms are fitted with a shower and a bathtub. A hairdryer and bathrobes are provided for everyday use. The hotel offers family rooms, non-smoking rooms and smoking rooms.</Text></Description><Description><Language>en</Language><Type>PropertyInformation</Type><Text>The hotel was built in 1996. Guests are welcomed at the accommodation, which has a total of 204 rooms. A lobby and a reception are available to travellers. Most storeys are accessible by lift. Amenities include a baggage storage service and a safe. Wireless internet access in public areas allows guests to stay connected. Among the culinary options available at the establishment are a restaurant, a dining area and a bar. Shopping facilities are also available. Travellers arriving by car can leave their vehicles in the garage or in the car park. Additional services include a babysitting service, a childcare service, room service and a laundry service.</Text></Description><Description><Language>en</Language><Type>AreaActivities</Type><Text>The terrace is a great place to while away the time. Leisure options at the accommodation include a gym, a spa, a sauna and beauty salon, or for a fee, massage treatments. Copyright GIATA 2004 - 2016. Multilingual, powered by www.giata.com for client no. 124887</Text></Description><Description><Language>en</Language><Type>PoliciesDisclaimers</Type><Text>The following credit cards are accepted at the establishment: American Express, VISA, Diners Club, JCB and MasterCard.</Text></Description><Description><Language>en</Language><Type>DiningFacilities</Type><Text>Breakfast can be booked.</Text></Description><Amenity><Text>Non smoking rooms</Text></Amenity><Amenity><Text>Safe</Text></Amenity><Amenity><Text>Fitness facility</Text></Amenity><Amenity><Text>Hotel restaurant</Text></Amenity><Amenity><Text>Hotel bar</Text></Amenity><Amenity><Text>Meeting rooms</Text></Amenity><Amenity><Text>Air conditioning</Text></Amenity><Amenity><Text>Mini-bar</Text></Amenity><Amenity><Text>Room service</Text></Amenity><Amenity><Text>Hair dryer</Text></Amenity><Amenity><Text>Satellite TV</Text></Amenity><Amenity><Text>Breakfast room</Text></Amenity><Rating><System>Stars</System><Score>50</Score><Description>Five star</Description></Rating></Hotel><Result id="20034730-0"><Room><RoomType code="1004525" text="Double Or Twin Standard" /><MealType code="1000041" text="Room only" /><Price amt="89.40" /><Guests><Adult id="-2" first="" last=""><Price amt="89.40" /></Adult></Guests></Room></Result><Result id="20034730-1"><Room><RoomType code="1002065" text="Triple Standard" /><MealType code="1000041" text="Room only" /><Price amt="134.00" /><Guests><Adult id="-3" first="" last=""><Price amt="134.00" /></Adult></Guests></Room></Result><Result id="20034730-2"><Room><RoomType code="1004525" text="Double Or Twin Standard" /><MealType code="1000018" text="Bed and breakfast" /><Price amt="134.00" /><Guests><Adult id="-4" first="" last=""><Price amt="134.00" /></Adult></Guests></Room></Result><Result id="20034730-3"><Room><RoomType code="1004525" text="Double Or Twin Standard" /><MealType code="1000019" text="Half board" /><Price amt="156.21" /><Guests><Adult id="-5" first="" last=""><Price amt="156.21" /></Adult></Guests></Room></Result><Result id="20034730-4"><Room><RoomType code="1001784" text="Single Deluxe" /><MealType code="1000041" text="Room only" /><Price amt="178.60" /><Guests><Adult id="-6" first="" last=""><Price amt="178.60" /></Adult></Guests></Room></Result><Result id="20034730-5"><Room><RoomType code="1002065" text="Triple Standard" /><MealType code="1000018" text="Bed and breakfast" /><Price amt="178.60" /><Guests><Adult id="-7" first="" last=""><Price amt="178.60" /></Adult></Guests></Room></Result><Result id="20034730-6"><Room><RoomType code="1004525" text="Double Or Twin Standard" /><MealType code="1000021" text="Full board" /><Price amt="178.60" /><Guests><Adult id="-8" first="" last=""><Price amt="178.60" /></Adult></Guests></Room></Result><Result id="20034730-7"><Room><RoomType code="1002065" text="Triple Standard" /><MealType code="1000019" text="Half board" /><Price amt="201.00" /><Guests><Adult id="-9" first="" last=""><Price amt="201.00" /></Adult></Guests></Room></Result><Result id="20034730-8"><Room><RoomType code="1001784" text="Single Deluxe" /><MealType code="1000018" text="Bed and breakfast" /><Price amt="223.20" /><Guests><Adult id="-10" first="" last=""><Price amt="223.20" /></Adult></Guests></Room></Result><Result id="20034730-9"><Room><RoomType code="1800284" text="DOUBLE SINGLE USE STANDARD" /><MealType code="1000041" text="Room only" /><Price amt="223.20" /><Guests><Adult id="-11" first="" last=""><Price amt="223.20" /></Adult></Guests></Room></Result><Result id="20034730-10"><Room><RoomType code="1002065" text="Triple Standard" /><MealType code="1000021" text="Full board" /><Price amt="223.20" /><Guests><Adult id="-12" first="" last=""><Price amt="223.20" /></Adult></Guests></Room></Result><Result id="20034730-11"><Room><RoomType code="1001784" text="Single Deluxe" /><MealType code="1000019" text="Half board" /><Price amt="245.60" /><Guests><Adult id="-13" first="" last=""><Price amt="245.60" /></Adult></Guests></Room></Result><Result id="20034730-12"><Room><RoomType code="1001784" text="Single Deluxe" /><MealType code="1000021" text="Full board" /><Price amt="267.80" /><Guests><Adult id="-14" first="" last=""><Price amt="267.80" /></Adult></Guests></Room></Result><Result id="20034730-13"><Room><RoomType code="1800284" text="DOUBLE SINGLE USE STANDARD" /><MealType code="1000018" text="Bed and breakfast" /><Price amt="267.80" /><Guests><Adult id="-15" first="" last=""><Price amt="267.80" /></Adult></Guests></Room></Result><Result id="20034730-14"><Room><RoomType code="1800284" text="DOUBLE SINGLE USE STANDARD" /><MealType code="1000019" text="Half board" /><Price amt="290.20" /><Guests><Adult id="-16" first="" last=""><Price amt="290.20" /></Adult></Guests></Room></Result><Result id="20034730-15"><Room><RoomType code="1800284" text="DOUBLE SINGLE USE STANDARD" /><MealType code="1000021" text="Full board" /><Price amt="312.41" /><Guests><Adult id="-17" first="" last=""><Price amt="312.41" /></Adult></Guests></Room></Result><Result id="20034730-16"><Room><RoomType code="1001690" text="Single Standard" /><MealType code="1000041" text="Room only" /><Price amt="357.20" /><Guests><Adult id="-18" first="" last=""><Price amt="357.20" /></Adult></Guests></Room></Result><Result id="20034730-17"><Room><RoomType code="1002210" text="Double Deluxe" /><MealType code="1000041" text="Room only" /><Price amt="401.80" /><Guests><Adult id="-19" first="" last=""><Price amt="401.80" /></Adult></Guests></Room></Result><Result id="20034730-18"><Room><RoomType code="1001690" text="Single Standard" /><MealType code="1000018" text="Bed and breakfast" /><Price amt="401.80" /><Guests><Adult id="-20" first="" last=""><Price amt="401.80" /></Adult></Guests></Room></Result><Result id="20034730-19"><Room><RoomType code="1001690" text="Single Standard" /><MealType code="1000019" text="Half board" /><Price amt="424.00" /><Guests><Adult id="-21" first="" last=""><Price amt="424.00" /></Adult></Guests></Room></Result><Result id="20034730-20"><Room><RoomType code="1002210" text="Double Deluxe" /><MealType code="1000018" text="Bed and breakfast" /><Price amt="446.40" /><Guests><Adult id="-22" first="" last=""><Price amt="446.40" /></Adult></Guests></Room></Result><Result id="20034730-21"><Room><RoomType code="1002211" text="Triple Deluxe" /><MealType code="1000041" text="Room only" /><Price amt="446.40" /><Guests><Adult id="-23" first="" last=""><Price amt="446.40" /></Adult></Guests></Room></Result><Result id="20034730-22"><Room><RoomType code="1001690" text="Single Standard" /><MealType code="1000021" text="Full board" /><Price amt="446.40" /><Guests><Adult id="-24" first="" last=""><Price amt="446.40" /></Adult></Guests></Room></Result><Result id="20034730-23"><Room><RoomType code="1002210" text="Double Deluxe" /><MealType code="1000019" text="Half board" /><Price amt="468.80" /><Guests><Adult id="-25" first="" last=""><Price amt="468.80" /></Adult></Guests></Room></Result><Result id="20034730-24"><Room><RoomType code="1002210" text="Double Deluxe" /><MealType code="1000021" text="Full board" /><Price amt="491.00" /><Guests><Adult id="-26" first="" last=""><Price amt="491.00" /></Adult></Guests></Room></Result><Result id="20034730-25"><Room><RoomType code="1002211" text="Triple Deluxe" /><MealType code="1000018" text="Bed and breakfast" /><Price amt="491.00" /><Guests><Adult id="-27" first="" last=""><Price amt="491.00" /></Adult></Guests></Room></Result><Result id="20034730-26"><Room><RoomType code="2142445" text="Room WITH DOUBLE BED" /><MealType code="1000041" text="Room only" /><Price amt="491.00" /><Guests><Adult id="-28" first="" last=""><Price amt="491.00" /></Adult></Guests></Room></Result><Result id="20034730-27"><Room><RoomType code="1002211" text="Triple Deluxe" /><MealType code="1000019" text="Half board" /><Price amt="513.40" /><Guests><Adult id="-29" first="" last=""><Price amt="513.40" /></Adult></Guests></Room></Result><Result id="20034730-28"><Room><RoomType code="1002211" text="Triple Deluxe" /><MealType code="1000021" text="Full board" /><Price amt="535.60" /><Guests><Adult id="-30" first="" last=""><Price amt="535.60" /></Adult></Guests></Room></Result><Result id="20034730-29"><Room><RoomType code="2142445" text="Room WITH DOUBLE BED" /><MealType code="1000018" text="Bed and breakfast" /><Price amt="535.60" /><Guests><Adult id="-31" first="" last=""><Price amt="535.60" /></Adult></Guests></Room></Result><Result id="20034730-30"><Room><RoomType code="2145163" text="Bed in dormitory FEMALE ROOM" /><MealType code="1000041" text="Room only" /><Price amt="535.60" /><Guests><Adult id="-32" first="" last=""><Price amt="535.60" /></Adult></Guests></Room></Result><Result id="20034730-31"><Room><RoomType code="2142445" text="Room WITH DOUBLE BED" /><MealType code="1000019" text="Half board" /><Price amt="558.00" /><Guests><Adult id="-33" first="" last=""><Price amt="558.00" /></Adult></Guests></Room></Result><Result id="20034730-32"><Room><RoomType code="2142445" text="Room WITH DOUBLE BED" /><MealType code="1000021" text="Full board" /><Price amt="580.20" /><Guests><Adult id="-34" first="" last=""><Price amt="580.20" /></Adult></Guests></Room></Result><Result id="20034730-33"><Room><RoomType code="2141413" text="Room CAPACITY 8" /><MealType code="1000041" text="Room only" /><Price amt="580.20" /><Guests><Adult id="-35" first="" last=""><Price amt="580.20" /></Adult></Guests></Room></Result><Result id="20034730-34"><Room><RoomType code="2145163" text="Bed in dormitory FEMALE ROOM" /><MealType code="1000018" text="Bed and breakfast" /><Price amt="580.20" /><Guests><Adult id="-36" first="" last=""><Price amt="580.20" /></Adult></Guests></Room></Result><Result id="20034730-35"><Room><RoomType code="2145163" text="Bed in dormitory FEMALE ROOM" /><MealType code="1000019" text="Half board" /><Price amt="602.60" /><Guests><Adult id="-37" first="" last=""><Price amt="602.60" /></Adult></Guests></Room></Result><Result id="20034730-36"><Room><RoomType code="2141413" text="Room CAPACITY 8" /><MealType code="1000018" text="Bed and breakfast" /><Price amt="625.00" /><Guests><Adult id="-38" first="" last=""><Price amt="625.00" /></Adult></Guests></Room></Result><Result id="20034730-37"><Room><RoomType code="2145163" text="Bed in dormitory FEMALE ROOM" /><MealType code="1000021" text="Full board" /><Price amt="625.00" /><Guests><Adult id="-39" first="" last=""><Price amt="625.00" /></Adult></Guests></Room></Result><Result id="20034730-38"><Room><RoomType code="1971263" text="Room Standard" /><MealType code="1000041" text="Room only" /><Price amt="625.00" /><Guests><Adult id="-40" first="" last=""><Price amt="625.00" /></Adult></Guests></Room></Result><Result id="20034730-39"><Room><RoomType code="2141413" text="Room CAPACITY 8" /><MealType code="1000019" text="Half board" /><Price amt="647.20" /><Guests><Adult id="-41" first="" last=""><Price amt="647.20" /></Adult></Guests></Room></Result><Result id="20034730-40"><Room><RoomType code="2141413" text="Room CAPACITY 8" /><MealType code="1000021" text="Full board" /><Price amt="669.60" /><Guests><Adult id="-42" first="" last=""><Price amt="669.60" /></Adult></Guests></Room></Result><Result id="20034730-41"><Room><RoomType code="1971263" text="Room Standard" /><MealType code="1000018" text="Bed and breakfast" /><Price amt="669.60" /><Guests><Adult id="-43" first="" last=""><Price amt="669.60" /></Adult></Guests></Room></Result><Result id="20034730-42"><Room><RoomType code="1971263" text="Room Standard" /><MealType code="1000019" text="Half board" /><Price amt="691.80" /><Guests><Adult id="-44" first="" last=""><Price amt="691.80" /></Adult></Guests></Room></Result><Result id="20034730-43"><Room><RoomType code="1002008" text="Twin Standard" /><MealType code="1000041" text="Room only" /><Price amt="714.20" /><Guests><Adult id="-45" first="" last=""><Price amt="714.20" /></Adult></Guests></Room></Result><Result id="20034730-44"><Room><RoomType code="1971263" text="Room Standard" /><MealType code="1000021" text="Full board" /><Price amt="714.20" /><Guests><Adult id="-46" first="" last=""><Price amt="714.20" /></Adult></Guests></Room></Result><Result id="20034730-45"><Room><RoomType code="1002008" text="Twin Standard" /><MealType code="1000018" text="Bed and breakfast" /><Price amt="758.80" /><Guests><Adult id="-47" first="" last=""><Price amt="758.80" /></Adult></Guests></Room></Result><Result id="20034730-46"><Room><RoomType code="1002008" text="Twin Standard" /><MealType code="1000019" text="Half board" /><Price amt="781.20" /><Guests><Adult id="-48" first="" last=""><Price amt="781.20" /></Adult></Guests></Room></Result><Result id="20034730-47"><Room><RoomType code="1002008" text="Twin Standard" /><MealType code="1000021" text="Full board" /><Price amt="803.40" /><Guests><Adult id="-49" first="" last=""><Price amt="803.40" /></Adult></Guests></Room></Result><Result id="20034730-48"><Room><RoomType code="1002066" text="Quadruple Standard" /><MealType code="1000041" text="Room only" /><Price amt="803.40" /><Guests><Adult id="-50" first="" last=""><Price amt="803.40" /></Adult></Guests></Room></Result><Result id="20034730-49"><Room><RoomType code="1002066" text="Quadruple Standard" /><MealType code="1000018" text="Bed and breakfast" /><Price amt="848.00" /><Guests><Adult id="-51" first="" last=""><Price amt="848.00" /></Adult></Guests></Room></Result><Result id="20034730-50"><Room><RoomType code="2141411" text="Room CAPACITY 6" /><MealType code="1000041" text="Room only" /><Price amt="848.00" /><Guests><Adult id="-52" first="" last=""><Price amt="848.00" /></Adult></Guests></Room></Result><Result id="20034730-51"><Room><RoomType code="1002066" text="Quadruple Standard" /><MealType code="1000019" text="Half board" /><Price amt="870.40" /><Guests><Adult id="-53" first="" last=""><Price amt="870.40" /></Adult></Guests></Room></Result><Result id="20034730-52"><Room><RoomType code="2141409" text="Room CAPACITY 5" /><MealType code="1000041" text="Room only" /><Price amt="892.60" /><Guests><Adult id="-54" first="" last=""><Price amt="892.60" /></Adult></Guests></Room></Result><Result id="20034730-53"><Room><RoomType code="1002066" text="Quadruple Standard" /><MealType code="1000021" text="Full board" /><Price amt="892.60" /><Guests><Adult id="-55" first="" last=""><Price amt="892.60" /></Adult></Guests></Room></Result><Result id="20034730-54"><Room><RoomType code="2141411" text="Room CAPACITY 6" /><MealType code="1000018" text="Bed and breakfast" /><Price amt="892.60" /><Guests><Adult id="-56" first="" last=""><Price amt="892.60" /></Adult></Guests></Room></Result><Result id="20034730-55"><Room><RoomType code="2141411" text="Room CAPACITY 6" /><MealType code="1000019" text="Half board" /><Price amt="915.00" /><Guests><Adult id="-57" first="" last=""><Price amt="915.00" /></Adult></Guests></Room></Result><Result id="20034730-56"><Room><RoomType code="2141409" text="Room CAPACITY 5" /><MealType code="1000018" text="Bed and breakfast" /><Price amt="937.40" /><Guests><Adult id="-58" first="" last=""><Price amt="937.40" /></Adult></Guests></Room></Result><Result id="20034730-57"><Room><RoomType code="2141411" text="Room CAPACITY 6" /><MealType code="1000021" text="Full board" /><Price amt="937.40" /><Guests><Adult id="-59" first="" last=""><Price amt="937.40" /></Adult></Guests></Room></Result><Result id="20034730-58"><Room><RoomType code="2141409" text="Room CAPACITY 5" /><MealType code="1000019" text="Half board" /><Price amt="959.60" /><Guests><Adult id="-60" first="" last=""><Price amt="959.60" /></Adult></Guests></Room></Result><Result id="20034730-59"><Room><RoomType code="1002196" text="Double Standard" /><MealType code="1000041" text="Room only" /><Price amt="982.00" /><Guests><Adult id="-61" first="" last=""><Price amt="982.00" /></Adult></Guests></Room></Result><Result id="20034730-60"><Room><RoomType code="2141409" text="Room CAPACITY 5" /><MealType code="1000021" text="Full board" /><Price amt="982.00" /><Guests><Adult id="-62" first="" last=""><Price amt="982.00" /></Adult></Guests></Room></Result><Result id="20034730-61"><Room><RoomType code="1002196" text="Double Standard" /><MealType code="1000018" text="Bed and breakfast" /><Price amt="1026.60" /><Guests><Adult id="-63" first="" last=""><Price amt="1026.60" /></Adult></Guests></Room></Result><Result id="20034730-62"><Room><RoomType code="2141412" text="Room CAPACITY 7" /><MealType code="1000041" text="Room only" /><Price amt="1026.60" /><Guests><Adult id="-64" first="" last=""><Price amt="1026.60" /></Adult></Guests></Room></Result><Result id="20034730-63"><Room><RoomType code="1002196" text="Double Standard" /><MealType code="1000019" text="Half board" /><Price amt="1048.80" /><Guests><Adult id="-65" first="" last=""><Price amt="1048.80" /></Adult></Guests></Room></Result><Result id="20034730-64"><Room><RoomType code="1002196" text="Double Standard" /><MealType code="1000021" text="Full board" /><Price amt="1071.20" /><Guests><Adult id="-66" first="" last=""><Price amt="1071.20" /></Adult></Guests></Room></Result><Result id="20034730-65"><Room><RoomType code="2141412" text="Room CAPACITY 7" /><MealType code="1000018" text="Bed and breakfast" /><Price amt="1071.20" /><Guests><Adult id="-67" first="" last=""><Price amt="1071.20" /></Adult></Guests></Room></Result><Result id="20034730-66"><Room><RoomType code="2141412" text="Room CAPACITY 7" /><MealType code="1000019" text="Half board" /><Price amt="1093.60" /><Guests><Adult id="-68" first="" last=""><Price amt="1093.60" /></Adult></Guests></Room></Result><Result id="20034730-67"><Room><RoomType code="2141412" text="Room CAPACITY 7" /><MealType code="1000021" text="Full board" /><Price amt="1115.80" /><Guests><Adult id="-69" first="" last=""><Price amt="1115.80" /></Adult></Guests></Room></Result><Result id="20034730-68"><Room><RoomType code="2142689" text="Bed in dormitory STANDARD" /><MealType code="1000041" text="Room only" /><Price amt="1294.40" /><Guests><Adult id="-70" first="" last=""><Price amt="1294.40" /></Adult></Guests></Room></Result><Result id="20034730-69"><Room><RoomType code="2145161" text="Bed in dormitory BUNK BED" /><MealType code="1000041" text="Room only" /><Price amt="1339.00" /><Guests><Adult id="-71" first="" last=""><Price amt="1339.00" /></Adult></Guests></Room></Result><Result id="20034730-70"><Room><RoomType code="2142689" text="Bed in dormitory STANDARD" /><MealType code="1000018" text="Bed and breakfast" /><Price amt="1339.00" /><Guests><Adult id="-72" first="" last=""><Price amt="1339.00" /></Adult></Guests></Room></Result><Result id="20034730-71"><Room><RoomType code="2142689" text="Bed in dormitory STANDARD" /><MealType code="1000019" text="Half board" /><Price amt="1361.21" /><Guests><Adult id="-73" first="" last=""><Price amt="1361.21" /></Adult></Guests></Room></Result><Result id="20034730-72"><Room><RoomType code="2145161" text="Bed in dormitory BUNK BED" /><MealType code="1000018" text="Bed and breakfast" /><Price amt="1383.60" /><Guests><Adult id="-74" first="" last=""><Price amt="1383.60" /></Adult></Guests></Room></Result><Result id="20034730-73"><Room><RoomType code="2142689" text="Bed in dormitory STANDARD" /><MealType code="1000021" text="Full board" /><Price amt="1383.60" /><Guests><Adult id="-75" first="" last=""><Price amt="1383.60" /></Adult></Guests></Room></Result><Result id="20034730-74"><Room><RoomType code="2145161" text="Bed in dormitory BUNK BED" /><MealType code="1000019" text="Half board" /><Price amt="1406.00" /><Guests><Adult id="-76" first="" last=""><Price amt="1406.00" /></Adult></Guests></Room></Result><Result id="20034730-75"><Room><RoomType code="2145161" text="Bed in dormitory BUNK BED" /><MealType code="1000021" text="Full board" /><Price amt="1428.20" /><Guests><Adult id="-77" first="" last=""><Price amt="1428.20" /></Adult></Guests></Room></Result><Result id="20034730-76"><Room><RoomType code="2097911" text="TWIN CAPACITY 1" /><MealType code="1000041" text="Room only" /><Price amt="1472.80" /><Guests><Adult id="-78" first="" last=""><Price amt="1472.80" /></Adult></Guests></Room></Result><Result id="20034730-77"><Room><RoomType code="2141414" text="Room CAPACITY 9" /><MealType code="1000041" text="Room only" /><Price amt="1517.41" /><Guests><Adult id="-79" first="" last=""><Price amt="1517.41" /></Adult></Guests></Room></Result><Result id="20034730-78"><Room><RoomType code="2097911" text="TWIN CAPACITY 1" /><MealType code="1000018" text="Bed and breakfast" /><Price amt="1517.41" /><Guests><Adult id="-80" first="" last=""><Price amt="1517.41" /></Adult></Guests></Room></Result><Result id="20034730-79"><Room><RoomType code="2097911" text="TWIN CAPACITY 1" /><MealType code="1000019" text="Half board" /><Price amt="1539.80" /><Guests><Adult id="-81" first="" last=""><Price amt="1539.80" /></Adult></Guests></Room></Result><Result id="20034730-80"><Room><RoomType code="2141414" text="Room CAPACITY 9" /><MealType code="1000018" text="Bed and breakfast" /><Price amt="1562.20" /><Guests><Adult id="-82" first="" last=""><Price amt="1562.20" /></Adult></Guests></Room></Result><Result id="20034730-81"><Room><RoomType code="2097911" text="TWIN CAPACITY 1" /><MealType code="1000021" text="Full board" /><Price amt="1562.20" /><Guests><Adult id="-83" first="" last=""><Price amt="1562.20" /></Adult></Guests></Room></Result><Result id="20034730-82"><Room><RoomType code="2141414" text="Room CAPACITY 9" /><MealType code="1000019" text="Half board" /><Price amt="1584.40" /><Guests><Adult id="-84" first="" last=""><Price amt="1584.40" /></Adult></Guests></Room></Result><Result id="20034730-83"><Room><RoomType code="2141414" text="Room CAPACITY 9" /><MealType code="1000021" text="Full board" /><Price amt="1606.80" /><Guests><Adult id="-85" first="" last=""><Price amt="1606.80" /></Adult></Guests></Room></Result><Result id="20034730-84"><Room><RoomType code="2145162" text="Bed in dormitory MALE ROOM" /><MealType code="1000041" text="Room only" /><Price amt="1606.80" /><Guests><Adult id="-86" first="" last=""><Price amt="1606.80" /></Adult></Guests></Room></Result><Result id="20034730-85"><Room><RoomType code="2145162" text="Bed in dormitory MALE ROOM" /><MealType code="1000018" text="Bed and breakfast" /><Price amt="1651.40" /><Guests><Adult id="-87" first="" last=""><Price amt="1651.40" /></Adult></Guests></Room></Result><Result id="20034730-86"><Room><RoomType code="2145162" text="Bed in dormitory MALE ROOM" /><MealType code="1000019" text="Half board" /><Price amt="1673.61" /><Guests><Adult id="-88" first="" last=""><Price amt="1673.61" /></Adult></Guests></Room></Result><Result id="20034730-87"><Room><RoomType code="2145162" text="Bed in dormitory MALE ROOM" /><MealType code="1000021" text="Full board" /><Price amt="1696.00" /><Guests><Adult id="-89" first="" last=""><Price amt="1696.00" /></Adult></Guests></Room></Result><Result id="20034730-88"><Room><RoomType code="1002038" text="Suite Executive" /><MealType code="1000041" text="Room only" /><Price amt="94.00" /><Guests><Adult id="-90" first="" last=""><Price amt="94.00" /></Adult></Guests></Room></Result><Result id="20034730-89"><Room><RoomType code="1004527" text="Double Or Twin Deluxe" /><MealType code="1000041" text="Room only" /><Price amt="141.00" /><Guests><Adult id="-91" first="" last=""><Price amt="141.00" /></Adult></Guests></Room></Result><Result id="20034730-90"><Room><RoomType code="1002038" text="Suite Executive" /><MealType code="1000018" text="Bed and breakfast" /><Price amt="141.00" /><Guests><Adult id="-92" first="" last=""><Price amt="141.00" /></Adult></Guests></Room></Result><Result id="20034730-91"><Room><RoomType code="1002038" text="Suite Executive" /><MealType code="1000019" text="Half board" /><Price amt="164.60" /><Guests><Adult id="-93" first="" last=""><Price amt="164.60" /></Adult></Guests></Room></Result><Result id="20034730-92"><Room><RoomType code="1004526" text="Double Or Twin Superior" /><MealType code="1000041" text="Room only" /><Price amt="188.00" /><Guests><Adult id="-94" first="" last=""><Price amt="188.00" /></Adult></Guests></Room></Result><Result id="20034730-93"><Room><RoomType code="1004527" text="Double Or Twin Deluxe" /><MealType code="1000018" text="Bed and breakfast" /><Price amt="188.00" /><Guests><Adult id="-95" first="" last=""><Price amt="188.00" /></Adult></Guests></Room></Result><Result id="20034730-94"><Room><RoomType code="1002038" text="Suite Executive" /><MealType code="1000021" text="Full board" /><Price amt="188.00" /><Guests><Adult id="-96" first="" last=""><Price amt="188.00" /></Adult></Guests></Room></Result><Result id="20034730-95"><Room><RoomType code="1004527" text="Double Or Twin Deluxe" /><MealType code="1000019" text="Half board" /><Price amt="211.40" /><Guests><Adult id="-97" first="" last=""><Price amt="211.40" /></Adult></Guests></Room></Result><Result id="20034730-96"><Room><RoomType code="1004526" text="Double Or Twin Superior" /><MealType code="1000018" text="Bed and breakfast" /><Price amt="235.00" /><Guests><Adult id="-98" first="" last=""><Price amt="235.00" /></Adult></Guests></Room></Result><Result id="20034730-97"><Room><RoomType code="1004527" text="Double Or Twin Deluxe" /><MealType code="1000021" text="Full board" /><Price amt="235.00" /><Guests><Adult id="-99" first="" last=""><Price amt="235.00" /></Adult></Guests></Room></Result><Result id="20034730-98"><Room><RoomType code="1800357" text="DOUBLE SINGLE USE SUPERIOR" /><MealType code="1000041" text="Room only" /><Price amt="235.00" /><Guests><Adult id="-100" first="" last=""><Price amt="235.00" /></Adult></Guests></Room></Result><Result id="20034730-99"><Room><RoomType code="1004526" text="Double Or Twin Superior" /><MealType code="1000019" text="Half board" /><Price amt="258.40" /><Guests><Adult id="-101" first="" last=""><Price amt="258.40" /></Adult></Guests></Room></Result><Result id="20034730-100"><Room><RoomType code="1004526" text="Double Or Twin Superior" /><MealType code="1000021" text="Full board" /><Price amt="282.00" /><Guests><Adult id="-102" first="" last=""><Price amt="282.00" /></Adult></Guests></Room></Result><Result id="20034730-101"><Room><RoomType code="1800322" text="DOUBLE SINGLE USE DELUXE" /><MealType code="1000041" text="Room only" /><Price amt="282.00" /><Guests><Adult id="-103" first="" last=""><Price amt="282.00" /></Adult></Guests></Room></Result><Result id="20034730-102"><Room><RoomType code="1800357" text="DOUBLE SINGLE USE SUPERIOR" /><MealType code="1000018" text="Bed and breakfast" /><Price amt="282.00" /><Guests><Adult id="-104" first="" last=""><Price amt="282.00" /></Adult></Guests></Room></Result><Result id="20034730-103"><Room><RoomType code="1800357" text="DOUBLE SINGLE USE SUPERIOR" /><MealType code="1000019" text="Half board" /><Price amt="305.40" /><Guests><Adult id="-105" first="" last=""><Price amt="305.40" /></Adult></Guests></Room></Result><Result id="20034730-104"><Room><RoomType code="1800322" text="DOUBLE SINGLE USE DELUXE" /><MealType code="1000018" text="Bed and breakfast" /><Price amt="329.00" /><Guests><Adult id="-106" first="" last=""><Price amt="329.00" /></Adult></Guests></Room></Result><Result id="20034730-105"><Room><RoomType code="1800357" text="DOUBLE SINGLE USE SUPERIOR" /><MealType code="1000021" text="Full board" /><Price amt="329.00" /><Guests><Adult id="-107" first="" last=""><Price amt="329.00" /></Adult></Guests></Room></Result><Result id="20034730-106"><Room><RoomType code="1001785" text="Single Superior" /><MealType code="1000041" text="Room only" /><Price amt="329.00" /><Guests><Adult id="-108" first="" last=""><Price amt="329.00" /></Adult></Guests></Room></Result><Result id="20034730-107"><Room><RoomType code="1800322" text="DOUBLE SINGLE USE DELUXE" /><MealType code="1000019" text="Half board" /><Price amt="352.40" /><Guests><Adult id="-109" first="" last=""><Price amt="352.40" /></Adult></Guests></Room></Result><Result id="20034730-108"><Room><RoomType code="1800322" text="DOUBLE SINGLE USE DELUXE" /><MealType code="1000021" text="Full board" /><Price amt="375.80" /><Guests><Adult id="-110" first="" last=""><Price amt="375.80" /></Adult></Guests></Room></Result><Result id="20034730-109"><Room><RoomType code="1001785" text="Single Superior" /><MealType code="1000018" text="Bed and breakfast" /><Price amt="375.80" /><Guests><Adult id="-111" first="" last=""><Price amt="375.80" /></Adult></Guests></Room></Result><Result id="20034730-110"><Room><RoomType code="1001785" text="Single Superior" /><MealType code="1000019" text="Half board" /><Price amt="399.40" /><Guests><Adult id="-112" first="" last=""><Price amt="399.40" /></Adult></Guests></Room></Result><Result id="20034730-111"><Room><RoomType code="1001785" text="Single Superior" /><MealType code="1000021" text="Full board" /><Price amt="422.80" /><Guests><Adult id="-113" first="" last=""><Price amt="422.80" /></Adult></Guests></Room></Result><Result id="20034730-112"><Room><RoomType code="1002214" text="Triple Superior" /><MealType code="1000041" text="Room only" /><Price amt="422.80" /><Guests><Adult id="-114" first="" last=""><Price amt="422.80" /></Adult></Guests></Room></Result><Result id="20034730-113"><Room><RoomType code="1002213" text="Double Superior" /><MealType code="1000041" text="Room only" /><Price amt="469.80" /><Guests><Adult id="-115" first="" last=""><Price amt="469.80" /></Adult></Guests></Room></Result><Result id="20034730-114"><Room><RoomType code="1002214" text="Triple Superior" /><MealType code="1000018" text="Bed and breakfast" /><Price amt="469.80" /><Guests><Adult id="-116" first="" last=""><Price amt="469.80" /></Adult></Guests></Room></Result><Result id="20034730-115"><Room><RoomType code="1002214" text="Triple Superior" /><MealType code="1000019" text="Half board" /><Price amt="493.40" /><Guests><Adult id="-117" first="" last=""><Price amt="493.40" /></Adult></Guests></Room></Result><Result id="20034730-116"><Room><RoomType code="1002513" text="Twin Deluxe" /><MealType code="1000041" text="Room only" /><Price amt="516.80" /><Guests><Adult id="-118" first="" last=""><Price amt="516.80" /></Adult></Guests></Room></Result><Result id="20034730-117"><Room><RoomType code="1002213" text="Double Superior" /><MealType code="1000018" text="Bed and breakfast" /><Price amt="516.80" /><Guests><Adult id="-119" first="" last=""><Price amt="516.80" /></Adult></Guests></Room></Result><Result id="20034730-118"><Room><RoomType code="1002214" text="Triple Superior" /><MealType code="1000021" text="Full board" /><Price amt="516.80" /><Guests><Adult id="-120" first="" last=""><Price amt="516.80" /></Adult></Guests></Room></Result><Result id="20034730-119"><Room><RoomType code="1002213" text="Double Superior" /><MealType code="1000019" text="Half board" /><Price amt="540.20" /><Guests><Adult id="-121" first="" last=""><Price amt="540.20" /></Adult></Guests></Room></Result><Result id="20034730-120"><Room><RoomType code="1002513" text="Twin Deluxe" /><MealType code="1000018" text="Bed and breakfast" /><Price amt="563.80" /><Guests><Adult id="-122" first="" last=""><Price amt="563.80" /></Adult></Guests></Room></Result><Result id="20034730-121"><Room><RoomType code="1002213" text="Double Superior" /><MealType code="1000021" text="Full board" /><Price amt="563.80" /><Guests><Adult id="-123" first="" last=""><Price amt="563.80" /></Adult></Guests></Room></Result><Result id="20034730-122"><Room><RoomType code="1002009" text="Twin Superior" /><MealType code="1000041" text="Room only" /><Price amt="563.80" /><Guests><Adult id="-124" first="" last=""><Price amt="563.80" /></Adult></Guests></Room></Result><Result id="20034730-123"><Room><RoomType code="1002513" text="Twin Deluxe" /><MealType code="1000019" text="Half board" /><Price amt="587.20" /><Guests><Adult id="-125" first="" last=""><Price amt="587.20" /></Adult></Guests></Room></Result><Result id="20034730-124"><Room><RoomType code="1002513" text="Twin Deluxe" /><MealType code="1000021" text="Full board" /><Price amt="610.80" /><Guests><Adult id="-126" first="" last=""><Price amt="610.80" /></Adult></Guests></Room></Result><Result id="20034730-125"><Room><RoomType code="1002009" text="Twin Superior" /><MealType code="1000018" text="Bed and breakfast" /><Price amt="610.80" /><Guests><Adult id="-127" first="" last=""><Price amt="610.80" /></Adult></Guests></Room></Result><Result id="20034730-126"><Room><RoomType code="1002009" text="Twin Superior" /><MealType code="1000019" text="Half board" /><Price amt="634.20" /><Guests><Adult id="-128" first="" last=""><Price amt="634.20" /></Adult></Guests></Room></Result><Result id="20034730-127"><Room><RoomType code="1002009" text="Twin Superior" /><MealType code="1000021" text="Full board" /><Price amt="657.80" /><Guests><Adult id="-129" first="" last=""><Price amt="657.80" /></Adult></Guests></Room></Result></HotelAvailability></AvailabilitySearchResult>