<?xml version="1.0" encoding="utf-8"?><AvailabilitySearchResult xmlns:xsd="http://www.w3.org/2001/XMLSchema" xmlns:xsi="http://www.w3.org/2001/XMLSchema-instance"><Currency>GBP</Currency><Warning>
</Warning><TestMode>false</TestMode><HotelAvailability><Hotel id="55106742" name="Hammersmith One Apartments" type="Apartments" stars="3" rank="1"><Region id="52887" name="Kensington &amp; Earls Court" /><Address><Address1>211-220a, Hamlet Gardens</Address1><Address2 /><City>London</City><State /><Zip>W6 0TS</Zip><Country>United Kingdom</Country><Tel>+44 20 3645 1799</Tel></Address><GeneralInfo /><Photo><Url>http://api.stuba.com/RXLImages/1136/57/01/25/570125_14030716430018600932.jpg</Url><Width>312</Width><Height>235</Height><Bytes>9185</Bytes><ThumbnailUrl>http://api.stuba.com/RXLImages/1136/57/01/25/570125_14030716430018600932thumb.jpg</ThumbnailUrl><ThumbnailWidth>92</ThumbnailWidth><ThumbnailHeight>70</ThumbnailHeight><ThumbnailBytes>1912</ThumbnailBytes><PhotoType>ExternalViewOfTheHotel</PhotoType></Photo><Photo><Url>http://api.stuba.com/RXLImages/1136/57/01/25/570125_14030716200018600161.jpg</Url><Width>312</Width><Height>235</Height><Bytes>10754</Bytes><ThumbnailUrl>http://api.stuba.com/RXLImages/1136/57/01/25/570125_14030716200018600161thumb.jpg</ThumbnailUrl><ThumbnailWidth>92</ThumbnailWidth><ThumbnailHeight>70</ThumbnailHeight><ThumbnailBytes>1983</ThumbnailBytes><PhotoType>ExternalViewOfTheHotel</PhotoType></Photo><Photo><Url>http://api.stuba.com/RXLImages/1136/57/01/25/570125_14030716200018600146.jpg</Url><Width>312</Width><Height>235</Height><Bytes>8016</Bytes><ThumbnailUrl>http://api.stuba.com/RXLImages/1136/57/01/25/570125_14030716200018600146thumb.jpg</ThumbnailUrl><ThumbnailWidth>92</ThumbnailWidth><ThumbnailHeight>70</ThumbnailHeight><ThumbnailBytes>1818</ThumbnailBytes><PhotoType>ExternalViewOfTheHotel</PhotoType></Photo><Photo><Url>http://api.stuba.com/RXLImages/1136/57/01/25/570125_14030716200018600145.jpg</Url><Width>312</Width><Height>235</Height><Bytes>7388</Bytes><ThumbnailUrl>http://api.stuba.com/RXLImages/1136/57/01/25/570125_14030716200018600145thumb.jpg</ThumbnailUrl><ThumbnailWidth>92</ThumbnailWidth><ThumbnailHeight>70</ThumbnailHeight><ThumbnailBytes>1684</ThumbnailBytes><PhotoType>ExternalViewOfTheHotel</PhotoType></Photo><Photo><Url>http://api.stuba.com/RXLImages/1136/57/01/25/570125_14030716200018600144.jpg</Url><Width>312</Width><Height>235</Height><Bytes>6069</Bytes><ThumbnailUrl>http://api.stuba.com/RXLImages/1136/57/01/25/570125_14030716200018600144thumb.jpg</ThumbnailUrl><ThumbnailWidth>92</ThumbnailWidth><ThumbnailHeight>70</ThumbnailHeight><ThumbnailBytes>1479</ThumbnailBytes><PhotoType>ExternalViewOfTheHotel</PhotoType></Photo><Description><Language>en</Language><Type>General</Type><Text>Hammersmith One Apartments is conveniently located in the popular Hammersmith area. Both business travelers and tourists can enjoy the hotel's facilities and services. Facilities like express check-in/check-out, Wi-Fi in public areas, family room, elevator are readily available for you to enjoy. Each guestroom is elegantly furnished and equipped with handy amenities. The hotel offers various recreational opportunities. Discover all London has to offer by making Hammersmith One Apartments your base. &lt;br/&gt;</Text></Description><Description><Language>en</Language><Type>Short</Type><Text>Hammersmith One Apartments is conveniently located in the popular Hammersmith area. Both business tr &lt;br/&gt;</Text></Description><Rating><System>Stars</System><Score>30</Score><Description>Three star</Description></Rating></Hotel><Result id="344719331-0"><Room><RoomType code="30696252" text="One Bedroom Executive (Double)" /><MealType code="1000041" text="Room only" /><Price amt="98.70" /><Guests><Adult id="-2" first="" last=""><Price amt="49.35" /></Adult><Adult id="-3" first="" last=""><Price amt="49.35" /></Adult></Guests><CanxFees><Fee><Amount amt="98.70" /></Fee></CanxFees></Room></Result><Result id="344719331-1"><Room><RoomType code="61166463" text="Two Bedroom Executive (Double)" /><MealType code="1000041" text="Room only" /><Price amt="122.12" /><Guests><Adult id="-4" first="" last=""><Price amt="61.06" /></Adult><Adult id="-5" first="" last=""><Price amt="61.06" /></Adult></Guests><CanxFees><Fee><Amount amt="122.12" /></Fee></CanxFees></Room></Result></HotelAvailability></AvailabilitySearchResult>