<?xml version="1.0" encoding="utf-8"?><AvailabilitySearchResult xmlns:xsd="http://www.w3.org/2001/XMLSchema" xmlns:xsi="http://www.w3.org/2001/XMLSchema-instance"><Currency>GBP</Currency><Warning>
</Warning><TestMode>false</TestMode><HotelAvailability><Hotel id="10124704" name="The St. Regis Moscow Nikolskaya" type="Hotel" stars="5" rank="1"><Region id="140587261" name="Central" /><Address><Address1>St. Nikolskaya 12</Address1><City>Moscow</City><Zip>109012</Zip><Country>Russia</Country><Tel>007 4959677776</Tel><Fax>007 4952872720</Fax><Email>reservations.moscow1@stregis.com</Email></Address><GeneralInfo /><Photo><Url>http://api.stuba.com/RXLImages/7/MOW-99hotel_Lobby_1.jpg</Url><Width>360</Width><Height>239</Height><Bytes>0</Bytes><ThumbnailUrl>http://api.stuba.com/RXLImages/7/MOW-99hotel_Lobby_1_thumb.jpg</ThumbnailUrl><ThumbnailWidth>80</ThumbnailWidth><ThumbnailHeight>60</ThumbnailHeight><ThumbnailBytes>0</ThumbnailBytes><PhotoType>LobbyRestaurantAndBar</PhotoType></Photo><Photo><Url>http://api.stuba.com/RXLImages/7/MOW-99hotel_Restaurant_1.jpg</Url><Width>360</Width><Height>240</Height><Bytes>0</Bytes><ThumbnailUrl>http://api.stuba.com/RXLImages/7/MOW-99hotel_Restaurant_1_thumb.jpg</ThumbnailUrl><ThumbnailWidth>80</ThumbnailWidth><ThumbnailHeight>60</ThumbnailHeight><ThumbnailBytes>0</ThumbnailBytes><PhotoType>LobbyRestaurantAndBar</PhotoType></Photo><Photo><Url>http://api.stuba.com/RXLImages/7/MOW-99hotel_Lobby_2.jpg</Url><Width>360</Width><Height>240</Height><Bytes>0</Bytes><ThumbnailUrl>http://api.stuba.com/RXLImages/7/MOW-99hotel_Lobby_2_thumb.jpg</ThumbnailUrl><ThumbnailWidth>80</ThumbnailWidth><ThumbnailHeight>60</ThumbnailHeight><ThumbnailBytes>0</ThumbnailBytes><PhotoType>LobbyRestaurantAndBar</PhotoType></Photo><Photo><Url>http://api.stuba.com/RXLImages/7/MOW-99hotel_Guest_Room_1.jpg</Url><Width>360</Width><Height>243</Height><Bytes>0</Bytes><ThumbnailUrl>http://api.stuba.com/RXLImages/7/MOW-99hotel_Guest_Room_1_thumb.jpg</ThumbnailUrl><ThumbnailWidth>80</ThumbnailWidth><ThumbnailHeight>60</ThumbnailHeight><ThumbnailBytes>0</ThumbnailBytes><PhotoType>OtherPhotos</PhotoType></Photo><Description><Language>en</Language><Type>General</Type><Text>&lt;p&gt;&lt;b&gt;Property Location&lt;/b&gt; &lt;br /&gt;The St. Regis Moscow Nikolskaya Hotel is in the heart of Moscow, walking distance from Polytechnical Museum and FSB Museum.  This 5-star hotel is close to Red Square and St. Basil's Cathedral.&lt;/p&gt;&lt;p&gt;&lt;b&gt;Rooms&lt;/b&gt; &lt;br /&gt;Make yourself at home in one of the 210 air-conditioned rooms featuring minibars and flat-screen televisions. Complimentary wireless Internet access keeps you connected, and satellite programming is available for your entertainment. Private bathrooms with separate bathtubs and showers feature complimentary toiletries and hair dryers. Conveniences include phones, as well as laptop-compatible safes and desks.&lt;/p&gt;&lt;p&gt;&lt;b&gt;Rec, Spa, Premium Amenities&lt;/b&gt; &lt;br /&gt;Take time to pamper yourself with a visit to the full-service spa. If you're looking for recreational opportunities, you'll find a health club, an indoor pool, and a 24-hour fitness center. This hotel also features complimentary wireless Internet access, concierge services, and wedding services. Guests can catch a ride to nearby destinations on the area shuttle (surcharge).&lt;/p&gt;&lt;p&gt;&lt;b&gt;Dining&lt;/b&gt; &lt;br /&gt;Enjoy a meal at a restaurant, or stay in and take advantage of the hotel's 24-hour room service. Relax with a refreshing drink at one of the 2 bars/lounges.&lt;/p&gt;&lt;p&gt;&lt;b&gt;Business, Other Amenities&lt;/b&gt; &lt;br /&gt;Featured amenities include a 24-hour business center, express check-out, and complimentary newspapers in the lobby. Planning an event in Moscow? This hotel has 4304 square feet (400 square meters) of space consisting of a conference center, conference space, and meeting rooms. For a surcharge, guests may use a roundtrip airport shuttle (available on request) and a train station pick-up service.&lt;/p&gt; &lt;br/&gt; Pets not allowed  Check-in time starts at 2 PM  Check-out time is Noon &lt;br/&gt; Enjoy a meal at a restaurant, or stay in and take advantage of the hotel's 24-hour room service. Relax with a refreshing drink at one of the 2 bars/lounges. &lt;br/&gt; Extra-person charges may apply and vary depending on hotel policy. &lt;br /&gt;Government-issued photo identification and a credit card or cash deposit are required at check-in for incidental charges. &lt;br /&gt;Special requests are subject to availability upon check-in and may incur additional charges. Special requests cannot be guaranteed.  &lt;ul&gt;&lt;li&gt;No onsite parking is available. &lt;/li&gt;&lt;/ul&gt; &lt;br/&gt; Take time to pamper yourself with a visit to the full-service spa. If you're looking for recreational opportunities, you'll find a health club, an indoor pool, and a 24-hour fitness center. This hotel also features complimentary wireless Internet access, concierge services, and wedding services. Guests can catch a ride to nearby destinations on the area shuttle (surcharge). &lt;br /&gt; Make yourself at home in one of the 210 air-conditioned rooms featuring minibars and flat-screen televisions. Complimentary wireless Internet access keeps you connected, and satellite programming is available for your entertainment. Private bathrooms with separate bathtubs and showers feature complimentary toiletries and hair dryers. Conveniences include phones, as well as laptop-compatible safes and desks.</Text></Description><Description><Language>en</Language><Type>SurroundingArea</Type><Text>The St. Regis Moscow Nikolskaya Hotel is in the heart of Moscow, walking distance from Polytechnical Museum and FSB Museum.  This 5-star hotel is close to Red Square and St. Basil's Cathedral. &lt;br/&gt; Distances are calculated in a straight line from the property's location to the point of interest or attraction, and may not reflect actual travel distance. &lt;br /&gt;&lt;br /&gt; Distances are displayed to the nearest 0.1 mile and kilometer. &lt;p&gt;Polytechnical Museum - 0.3 km / 0.2 mi &lt;br /&gt;FSB Museum - 0.4 km / 0.2 mi &lt;br /&gt;Maly Theatre - 0.4 km / 0.2 mi &lt;br /&gt;TSUM Department Store - 0.4 km / 0.2 mi &lt;br /&gt;Bolshoi Theatre - 0.4 km / 0.3 mi &lt;br /&gt;Revolution Square - 0.5 km / 0.3 mi &lt;br /&gt;War of 1812 Museum - 0.6 km / 0.4 mi &lt;br /&gt;Sanduny Bath House - 0.6 km / 0.4 mi &lt;br /&gt;Kazan Cathedral - 0.6 km / 0.4 mi &lt;br /&gt;GUM Department Store - 0.6 km / 0.4 mi &lt;br /&gt;Resurrection Gate - 0.6 km / 0.4 mi &lt;br /&gt;Gulag History Museum - 0.7 km / 0.4 mi &lt;br /&gt;Place of Skulls - 0.7 km / 0.4 mi &lt;br /&gt;State Historical Museum - 0.7 km / 0.4 mi &lt;br /&gt;Gostiny Dvor Arcade - 0.7 km / 0.4 mi &lt;br /&gt;&lt;/p&gt;&lt;p&gt;The preferred airport for The St. Regis Moscow Nikolskaya Hotel is Moscow (SVO-Sheremetyevo) - 26.5 km / 16.5 mi. &lt;/p&gt;</Text></Description><Description><Language>en</Language><Type>PoliciesDisclaimers</Type><Text>You must present a photo ID when checking in. Your credit card is charged at the time you book. Bed type and smoking preferences are not guaranteed.Your reservation is prepaid and is guaranteed for late arrival. The total charge includes all room charges and taxes, as well as fees for access and booking. Any incidental charges such as parking, phone calls, and room service will be handled directly between you and the property.</Text></Description><Description><Language>en</Language><Type>EssentialInfo</Type><Text>Extra-person charges may apply and vary depending on hotel policy. &lt;br /&gt;Government-issued photo identification and a credit card or cash deposit are required at check-in for incidental charges. &lt;br /&gt;Special requests are subject to availability upon check-in and may incur additional charges. Special requests cannot be guaranteed.  &lt;ul&gt;&lt;li&gt;No onsite parking is available. &lt;/li&gt;&lt;/ul&gt;</Text></Description><Rating><System>Stars</System><Score>50</Score><Description>Five star</Description></Rating></Hotel><Result id="344394576-0"><Room><RoomType code="61207115" text="Deluxe, Larger Guest Room, 1 King Deluxe, Larger Guest Room, 1 King" /><MealType code="1000041" text="Room only" /><Price amt="680.08" /><Guests><Adult id="-1193046472" first="" last=""><Price amt="340.04" /></Adult><Adult id="-1193046473" first="" last=""><Price amt="340.04" /></Adult></Guests><CanxFees><Fee><Amount amt="369.37000000000000000000000002" /></Fee></CanxFees></Room></Result><Result id="344394576-1"><Room><RoomType code="61207119" text="Deluxe, Larger Guest Room, 2 Twin/Single Bed(S) Deluxe, Larger Guest R" /><MealType code="1000041" text="Room only" /><Price amt="680.08" /><Guests><Adult id="-1193046474" first="" last=""><Price amt="340.04" /></Adult><Adult id="-1193046475" first="" last=""><Price amt="340.04" /></Adult></Guests><CanxFees><Fee><Amount amt="369.37000000000000000000000002" /></Fee></CanxFees></Room></Result><Result id="344394576-2"><Room><RoomType code="61207122" text="Deluxe, Larger Guest Room, 1 King Dyn Bdld Brkfast For 2 Rate, Bed And" /><MealType code="1" text="Breakfast" /><Price amt="825.52" /><Guests><Adult id="-1193046476" first="" last=""><Price amt="412.76" /></Adult><Adult id="-1193046477" first="" last=""><Price amt="412.76" /></Adult></Guests><CanxFees><Fee><Amount amt="446" /></Fee><Fee><Amount amt="444.04000000000000000000000001" /></Fee></CanxFees></Room></Result><Result id="344394576-3"><Room><RoomType code="61641932" text="Superior, Guest Room, 1 King Tour Op Dyn Bkfst For2 Rate, Tour Operato" /><MealType code="1" text="Breakfast" /><Price amt="703.60" /><Guests><Adult id="-1193046478" first="" last=""><Price amt="351.80" /></Adult><Adult id="-1193046479" first="" last=""><Price amt="351.80" /></Adult></Guests><CanxFees><Fee><Amount amt="387" /></Fee><Fee><Amount amt="381.08000000000000000000000002" /></Fee></CanxFees></Room></Result><Result id="344394576-4"><Room><RoomType code="61207126" text="St Regis Suite, Junior Suite, 1 King St Regis Suite, Junior Suite, 1 K" /><MealType code="1000041" text="Room only" /><Price amt="773.98" /><Guests><Adult id="-1193046480" first="" last=""><Price amt="386.99" /></Adult><Adult id="-1193046481" first="" last=""><Price amt="386.99" /></Adult></Guests><CanxFees><Fee><Amount amt="416.32000000000000000000000004" /></Fee></CanxFees></Room></Result><Result id="344394576-5"><Room><RoomType code="61207132" text="Astor Suite, 1 Bedroom Suite, 1 King Astor Suite, 1 Bedroom Suite, 1 K" /><MealType code="1000041" text="Room only" /><Price amt="961.56" /><Guests><Adult id="-1193046482" first="" last=""><Price amt="480.78" /></Adult><Adult id="-1193046483" first="" last=""><Price amt="480.78" /></Adult></Guests><CanxFees><Fee><Amount amt="510.11" /></Fee></CanxFees></Room></Result><Result id="344394576-6"><Room><RoomType code="61207138" text="Astor Suite, 1 Bedroom Suite, 1 King Dyn Bdld Brkfast For 2 Rate, Bed" /><MealType code="1" text="Breakfast" /><Price amt="1125.62" /><Guests><Adult id="-1193046484" first="" last=""><Price amt="562.81" /></Adult><Adult id="-1193046485" first="" last=""><Price amt="562.81" /></Adult></Guests><CanxFees><Fee><Amount amt="597" /></Fee><Fee><Amount amt="594.09" /></Fee></CanxFees></Room></Result><Result id="344394576-7"><Room><RoomType code="61641933" text="Deluxe, Larger Guest Room, 2 Twin/Single Bed(S) Tour Op Dyn Bkfst For2" /><MealType code="1" text="Breakfast" /><Price amt="773.98" /><Guests><Adult id="-1193046486" first="" last=""><Price amt="386.99" /></Adult><Adult id="-1193046487" first="" last=""><Price amt="386.99" /></Adult></Guests><CanxFees><Fee><Amount amt="418" /></Fee><Fee><Amount amt="416.32000000000000000000000004" /></Fee></CanxFees></Room></Result><Result id="344394576-8"><Room><RoomType code="61641934" text="St Regis Suite, Junior Suite, 1 King Tour Op Dyn Bkfst For2 Rate, Tour" /><MealType code="1" text="Breakfast" /><Price amt="867.66" /><Guests><Adult id="-1193046488" first="" last=""><Price amt="433.83" /></Adult><Adult id="-1193046489" first="" last=""><Price amt="433.83" /></Adult></Guests><CanxFees><Fee><Amount amt="469" /></Fee><Fee><Amount amt="463.16000000000000000000000002" /></Fee></CanxFees></Room></Result><Result id="344394576-9"><Room><RoomType code="61207145" text="Deluxe, Larger Guest Room, 1 King Dynamic Leisure Bundld Rate, Deposit" /><MealType code="1000041" text="Room only" /><Price amt="725.42" /><Guests><Adult id="-1193046490" first="" last=""><Price amt="362.71" /></Adult><Adult id="-1193046491" first="" last=""><Price amt="362.71" /></Adult></Guests><CanxFees><Fee><Amount amt="393.99000000000000000000000002" /></Fee></CanxFees></Room></Result><Result id="344394576-10"><Room><RoomType code="61207149" text="Astor Suite, 1 Bedroom Suite, 1 King Dynamic Leisure Bundld Rate, Depo" /><MealType code="1000041" text="Room only" /><Price amt="1025.62" /><Guests><Adult id="-1193046492" first="" last=""><Price amt="512.81" /></Adult><Adult id="-1193046493" first="" last=""><Price amt="512.81" /></Adult></Guests><CanxFees><Fee><Amount amt="544.03999999999999999999999996" /></Fee></CanxFees></Room></Result><Result id="344394576-11"><Room><RoomType code="61207151" text="St Regis Suite, Junior Suite, 1 King Dyn Bdld Brkfast For 2 Rate, Bed" /><MealType code="1" text="Breakfast" /><Price amt="925.62" /><Guests><Adult id="-1193046494" first="" last=""><Price amt="462.81" /></Adult><Adult id="-1193046495" first="" last=""><Price amt="462.81" /></Adult></Guests><CanxFees><Fee><Amount amt="500" /></Fee><Fee><Amount amt="494.09" /></Fee></CanxFees></Room></Result><Result id="344394576-12"><Room><RoomType code="61207153" text="Superior, Guest Room, 1 King Dyn Bdld Brkfast For 2 Rate, Bed And Brea" /><MealType code="1" text="Breakfast" /><Price amt="750.45" /><Guests><Adult id="-1193046496" first="" last=""><Price amt="375.22" /></Adult><Adult id="-1193046497" first="" last=""><Price amt="375.23" /></Adult></Guests><CanxFees><Fee><Amount amt="413" /></Fee><Fee><Amount amt="406.50999999999999999999999999" /></Fee></CanxFees></Room></Result><Result id="344394576-13"><Room><RoomType code="61641935" text="Astor Suite, 1 Bedroom Suite, 1 King Tour Op Dyn Bkfst For2 Rate, Tour" /><MealType code="1" text="Breakfast" /><Price amt="1055.26" /><Guests><Adult id="-1193046498" first="" last=""><Price amt="527.63" /></Adult><Adult id="-1193046499" first="" last=""><Price amt="527.63" /></Adult></Guests><CanxFees><Fee><Amount amt="560" /></Fee><Fee><Amount amt="556.95999999999999999999999995" /></Fee></CanxFees></Room></Result><Result id="344394576-14"><Room><RoomType code="61207157" text="Superior, Guest Room, 1 King Superior, Guest Room, 1 King" /><MealType code="1000041" text="Room only" /><Price amt="609.81" /><Guests><Adult id="-1193046500" first="" last=""><Price amt="304.90" /></Adult><Adult id="-1193046501" first="" last=""><Price amt="304.91" /></Adult></Guests><CanxFees><Fee><Amount amt="334.23000000000000000000000001" /></Fee></CanxFees></Room></Result><Result id="344394576-15"><Room><RoomType code="61207159" text="Deluxe, Larger Guest Room, 2 Twin/Single Bed(S) Dyn Bdld Brkfast For 2" /><MealType code="1" text="Breakfast" /><Price amt="825.52" /><Guests><Adult id="-1193046502" first="" last=""><Price amt="412.76" /></Adult><Adult id="-1193046503" first="" last=""><Price amt="412.76" /></Adult></Guests><CanxFees><Fee><Amount amt="446" /></Fee><Fee><Amount amt="444.04000000000000000000000001" /></Fee></CanxFees></Room></Result><Result id="344394576-16"><Room><RoomType code="61207161" text="Deluxe, Larger Guest Room, 2 Twin/Single Bed(S) Dynamic Leisure Bundld" /><MealType code="1000041" text="Room only" /><Price amt="725.42" /><Guests><Adult id="-1193046504" first="" last=""><Price amt="362.71" /></Adult><Adult id="-1193046505" first="" last=""><Price amt="362.71" /></Adult></Guests><CanxFees><Fee><Amount amt="393.99000000000000000000000002" /></Fee></CanxFees></Room></Result><Result id="344394576-17"><Room><RoomType code="61207162" text="Superior, Guest Room, 1 King Dynamic Leisure Bundld Rate, Deposit Requ" /><MealType code="1000041" text="Room only" /><Price amt="650.45" /><Guests><Adult id="-1193046506" first="" last=""><Price amt="325.22" /></Adult><Adult id="-1193046507" first="" last=""><Price amt="325.23" /></Adult></Guests><CanxFees><Fee><Amount amt="356.46000000000000000000000001" /></Fee></CanxFees></Room></Result><Result id="344394576-18"><Room><RoomType code="61641936" text="Deluxe, Larger Guest Room, 1 King Tour Op Dyn Bkfst For2 Rate, Tour Op" /><MealType code="1" text="Breakfast" /><Price amt="773.98" /><Guests><Adult id="-1193046508" first="" last=""><Price amt="386.99" /></Adult><Adult id="-1193046509" first="" last=""><Price amt="386.99" /></Adult></Guests><CanxFees><Fee><Amount amt="418" /></Fee><Fee><Amount amt="416.32000000000000000000000004" /></Fee></CanxFees></Room></Result><Result id="344394576-19"><Room><RoomType code="61207166" text="St Regis Suite, Junior Suite, 1 King Dynamic Leisure Bundld Rate, Depo" /><MealType code="1000041" text="Room only" /><Price amt="825.52" /><Guests><Adult id="-1193046510" first="" last=""><Price amt="412.76" /></Adult><Adult id="-1193046511" first="" last=""><Price amt="412.76" /></Adult></Guests><CanxFees><Fee><Amount amt="444.04000000000000000000000001" /></Fee></CanxFees></Room></Result></HotelAvailability></AvailabilitySearchResult>