<?xml version="1.0" encoding="utf-8"?><AvailabilitySearchResult xmlns:xsd="http://www.w3.org/2001/XMLSchema" xmlns:xsi="http://www.w3.org/2001/XMLSchema-instance"><Currency>GBP</Currency><Warning>
</Warning><TestMode>true</TestMode><HotelAvailability><Hotel id="57886" name="Lancaster Gate Hotel Hyde Park (Formerly Park Inn)" type="Hotel" stars="4" rank="1"><Region id="52917" name="Paddington &amp; Bayswater" /><Address><Address1>66 LANCASTER GATE BAYSWATER ROAD</Address1><City>LONDON W2 3NZ</City><Zip /><Country>UK - England</Country><Tel>44-20-72625090</Tel><Fax>44-20-77231244</Fax></Address><GeneralInfo /><Photo><Url>http://www.roomsxmldemo.com/RXLImages/7/LON-HYD3hotel_Exterior_1.jpg</Url><Width>360</Width><Height>270</Height><Bytes>113015</Bytes><ThumbnailUrl>http://www.roomsxmldemo.com/RXLImages/7/LON-HYD3hotel_Exterior_1_thumb.jpg</ThumbnailUrl><ThumbnailWidth>80</ThumbnailWidth><ThumbnailHeight>60</ThumbnailHeight><ThumbnailBytes>2492</ThumbnailBytes><PhotoType>ExternalViewOfTheHotel</PhotoType></Photo><Photo><Url>http://www.roomsxmldemo.com/RXLImages/7/LON-HYD3hotel_Bedroom_1.jpg</Url><Width>360</Width><Height>270</Height><Bytes>23527</Bytes><ThumbnailUrl>http://www.roomsxmldemo.com/RXLImages/7/LON-HYD3hotel_Bedroom_1_thumb.jpg</ThumbnailUrl><ThumbnailWidth>80</ThumbnailWidth><ThumbnailHeight>60</ThumbnailHeight><ThumbnailBytes>1954</ThumbnailBytes><PhotoType>ViewOfAGuestRoom</PhotoType></Photo><Photo><Url>http://www.roomsxmldemo.com/RXLImages/7/LON-HYD3hotel_Bar_1.jpg</Url><Width>360</Width><Height>270</Height><Bytes>112876</Bytes><ThumbnailUrl>http://www.roomsxmldemo.com/RXLImages/7/LON-HYD3hotel_Bar_1_thumb.jpg</ThumbnailUrl><ThumbnailWidth>80</ThumbnailWidth><ThumbnailHeight>60</ThumbnailHeight><ThumbnailBytes>2112</ThumbnailBytes><PhotoType>LobbyRestaurantAndBar</PhotoType></Photo><Photo><Url>http://www.roomsxmldemo.com/RXLImages/7/LON-HYD3hotel_Lounge_1.jpg</Url><Width>360</Width><Height>270</Height><Bytes>57053</Bytes><ThumbnailUrl>http://www.roomsxmldemo.com/RXLImages/7/LON-HYD3hotel_Lounge_1_thumb.jpg</ThumbnailUrl><ThumbnailWidth>80</ThumbnailWidth><ThumbnailHeight>60</ThumbnailHeight><ThumbnailBytes>1871</ThumbnailBytes><PhotoType>OtherPhotos</PhotoType></Photo><Photo><Url>http://www.roomsxmldemo.com/RXLImages/7/LON-HYD3hotel_Entrance_1.jpg</Url><Width>360</Width><Height>270</Height><Bytes>90667</Bytes><ThumbnailUrl>http://www.roomsxmldemo.com/RXLImages/7/LON-HYD3hotel_Entrance_1_thumb.jpg</ThumbnailUrl><ThumbnailWidth>80</ThumbnailWidth><ThumbnailHeight>60</ThumbnailHeight><ThumbnailBytes>2192</ThumbnailBytes><PhotoType>OtherPhotos</PhotoType></Photo><Photo><Url>http://www.roomsxmldemo.com/RXLImages/7/LON-HYD3hotel_Reception_1.jpg</Url><Width>360</Width><Height>270</Height><Bytes>93971</Bytes><ThumbnailUrl>http://www.roomsxmldemo.com/RXLImages/7/LON-HYD3hotel_Reception_1_thumb.jpg</ThumbnailUrl><ThumbnailWidth>80</ThumbnailWidth><ThumbnailHeight>60</ThumbnailHeight><ThumbnailBytes>1800</ThumbnailBytes><PhotoType>OtherPhotos</PhotoType></Photo><Description><Language>en</Language><Type>General</Type><Text>A contemporary four star hotel which also boasts a modern fitness centre with state of the art gymnasium equipment. 08/04 RP</Text></Description><Description><Language>en</Language><Type>SurroundingArea</Type><Text>The hotel is situated in Lancaster Gate, approximately one mile along the Bayswater Road from Marble Arch.</Text></Description><Description><Language>en</Language><Type>RoomTypes</Type><Text>The comfortable and well appointed guest rooms all feature en-suite bathrooms, remote control colour television with satellite channels, direct dial telephones, voicemail, ISDN modems, radio, air-conditioning, garment press and coffee/ tea making facilities.</Text></Description><Description><Language>en</Language><Type>PropertyInformation</Type><Text>A traditional building, quite grand in appearance with a graceful Edwardian facade.</Text></Description><Description><Language>en</Language><Type>DiningFacilities</Type><Text>The main restaurant, serving the best of British and International cuisine is located on the ground floor, traditionally decorated in dark wood furniture, leather seating, traditional pictures and lighting.</Text></Description><Description><Language>en</Language><Type>Short</Type><Text>The small lobby is traditionally decorated with leather seating.</Text></Description><Amenity><Text>Direct Dial Telephone</Text></Amenity><Rating><System>Stars</System><Score>40</Score><Description>Four star</Description></Rating></Hotel><Result id="19618951-0"><Room><RoomType code="1286415" text="Twin (Standard Twin)" /><MealType code="1000030" text="Full Breakfast" /><Price amt="211.30" /><Guests><Adult id="-76695846"><Price amt="105.66" /></Adult><Adult id="-76695847"><Price amt="105.64" /></Adult></Guests><CanxFees><Fee><Amount amt="211.30" /></Fee></CanxFees></Room></Result><Result id="19618951-1"><Room><RoomType code="1832194" text="Double (Standard Twin)" /><MealType code="1000030" text="Full Breakfast" /><Price amt="211.30" /><Guests><Adult id="-76695848"><Price amt="105.66" /></Adult><Adult id="-76695849"><Price amt="105.64" /></Adult></Guests><CanxFees><Fee><Amount amt="211.30" /></Fee></CanxFees></Room></Result><Result id="19618951-2"><Room><RoomType code="1001690" text="Single Standard" /><MealType code="1000041" text="Room only" /><Price amt="115.10" /><Guests><Adult id="-153391691" first="" last=""><Price amt="57.55" /></Adult><Adult id="-153391692" first="" last=""><Price amt="57.55" /></Adult></Guests><CanxFees><Fee><Amount amt="115.10" /></Fee></CanxFees></Room></Result><Result id="19618951-3"><Room><RoomType code="1001690" text="Single Standard" /><MealType code="1000018" text="Bed and breakfast" /><Price amt="230.20" /><Guests><Adult id="-153391693" first="" last=""><Price amt="115.10" /></Adult><Adult id="-153391694" first="" last=""><Price amt="115.10" /></Adult></Guests><CanxFees><Fee><Amount amt="230.20" /></Fee></CanxFees></Room></Result><Result id="19618951-4"><Room><RoomType code="1001690" text="Single Standard" /><MealType code="1000019" text="Half board" /><Price amt="287.80" /><Guests><Adult id="-153391695" first="" last=""><Price amt="143.90" /></Adult><Adult id="-153391696" first="" last=""><Price amt="143.90" /></Adult></Guests><CanxFees><Fee><Amount amt="287.80" /></Fee></CanxFees></Room></Result><Result id="19618951-5"><Room><RoomType code="1001690" text="Single Standard" /><MealType code="1000021" text="Full board" /><Price amt="345.40" /><Guests><Adult id="-153391697" first="" last=""><Price amt="172.70" /></Adult><Adult id="-153391698" first="" last=""><Price amt="172.70" /></Adult></Guests><CanxFees><Fee><Amount amt="345.40" /></Fee></CanxFees></Room></Result><Result id="19618951-6"><Room><RoomType code="1002196" text="Double Standard" /><MealType code="1000019" text="Half board" /><Price amt="402.90" /><Guests><Adult id="-153391699" first="" last=""><Price amt="201.45" /></Adult><Adult id="-153391700" first="" last=""><Price amt="201.45" /></Adult></Guests><CanxFees><Fee><Amount amt="402.90" /></Fee></CanxFees></Room></Result><Result id="19618951-7"><Room><RoomType code="1002196" text="Double Standard" /><MealType code="1000021" text="Full board" /><Price amt="460.50" /><Guests><Adult id="-153391701" first="" last=""><Price amt="230.25" /></Adult><Adult id="-153391702" first="" last=""><Price amt="230.25" /></Adult></Guests><CanxFees><Fee><Amount amt="460.50" /></Fee></CanxFees></Room></Result><Result id="19618951-8"><Room><RoomType code="2062736" text="DOUBLE PROMO" /><MealType code="1000041" text="Room only" /><Price amt="805.80" /><Guests><Adult id="-153391703" first="" last=""><Price amt="402.90" /></Adult><Adult id="-153391704" first="" last=""><Price amt="402.90" /></Adult></Guests><CanxFees><Fee><Amount amt="805.80" /></Fee></CanxFees></Room></Result><Result id="19618951-9"><Room><RoomType code="2062736" text="DOUBLE PROMO" /><MealType code="1000018" text="Bed and breakfast" /><Price amt="920.90" /><Guests><Adult id="-153391705" first="" last=""><Price amt="460.45" /></Adult><Adult id="-153391706" first="" last=""><Price amt="460.45" /></Adult></Guests><CanxFees><Fee><Amount amt="920.90" /></Fee></CanxFees></Room></Result><Result id="19618951-10"><Room><RoomType code="2062736" text="DOUBLE PROMO" /><MealType code="1000019" text="Half board" /><Price amt="978.40" /><Guests><Adult id="-153391707" first="" last=""><Price amt="489.20" /></Adult><Adult id="-153391708" first="" last=""><Price amt="489.20" /></Adult></Guests><CanxFees><Fee><Amount amt="978.40" /></Fee></CanxFees></Room></Result><Result id="19618951-11"><Room><RoomType code="2062736" text="DOUBLE PROMO" /><MealType code="1000021" text="Full board" /><Price amt="1036.00" /><Guests><Adult id="-153391709" first="" last=""><Price amt="518.00" /></Adult><Adult id="-153391710" first="" last=""><Price amt="518.00" /></Adult></Guests><CanxFees><Fee><Amount amt="1036.00" /></Fee></CanxFees></Room></Result><Result id="19618951-12"><Room><RoomType code="2062720" text="SINGLE PROMO" /><MealType code="1000041" text="Room only" /><Price amt="1553.90" /><Guests><Adult id="-153391711" first="" last=""><Price amt="776.95" /></Adult><Adult id="-153391712" first="" last=""><Price amt="776.95" /></Adult></Guests><CanxFees><Fee><Amount amt="1553.90" /></Fee></CanxFees></Room></Result><Result id="19618951-13"><Room><RoomType code="2109512" text="DOUBLE SINGLE USE PROMO" /><MealType code="1000041" text="Room only" /><Price amt="1669.00" /><Guests><Adult id="-153391713" first="" last=""><Price amt="834.50" /></Adult><Adult id="-153391714" first="" last=""><Price amt="834.50" /></Adult></Guests><CanxFees><Fee><Amount amt="1669.00" /></Fee></CanxFees></Room></Result><Result id="19618951-14"><Room><RoomType code="2062720" text="SINGLE PROMO" /><MealType code="1000018" text="Bed and breakfast" /><Price amt="1669.00" /><Guests><Adult id="-153391715" first="" last=""><Price amt="834.50" /></Adult><Adult id="-153391716" first="" last=""><Price amt="834.50" /></Adult></Guests><CanxFees><Fee><Amount amt="1669.00" /></Fee></CanxFees></Room></Result><Result id="19618951-15"><Room><RoomType code="2062720" text="SINGLE PROMO" /><MealType code="1000019" text="Half board" /><Price amt="1726.60" /><Guests><Adult id="-153391717" first="" last=""><Price amt="863.30" /></Adult><Adult id="-153391718" first="" last=""><Price amt="863.30" /></Adult></Guests><CanxFees><Fee><Amount amt="1726.60" /></Fee></CanxFees></Room></Result><Result id="19618951-16"><Room><RoomType code="2109512" text="DOUBLE SINGLE USE PROMO" /><MealType code="1000018" text="Bed and breakfast" /><Price amt="1784.10" /><Guests><Adult id="-153391719" first="" last=""><Price amt="892.05" /></Adult><Adult id="-153391720" first="" last=""><Price amt="892.05" /></Adult></Guests><CanxFees><Fee><Amount amt="1784.10" /></Fee></CanxFees></Room></Result><Result id="19618951-17"><Room><RoomType code="2062720" text="SINGLE PROMO" /><MealType code="1000021" text="Full board" /><Price amt="1784.10" /><Guests><Adult id="-153391721" first="" last=""><Price amt="892.05" /></Adult><Adult id="-153391722" first="" last=""><Price amt="892.05" /></Adult></Guests><CanxFees><Fee><Amount amt="1784.10" /></Fee></CanxFees></Room></Result><Result id="19618951-18"><Room><RoomType code="2109512" text="DOUBLE SINGLE USE PROMO" /><MealType code="1000019" text="Half board" /><Price amt="1841.70" /><Guests><Adult id="-153391723" first="" last=""><Price amt="920.85" /></Adult><Adult id="-153391724" first="" last=""><Price amt="920.85" /></Adult></Guests><CanxFees><Fee><Amount amt="1841.70" /></Fee></CanxFees></Room></Result><Result id="19618951-19"><Room><RoomType code="2109512" text="DOUBLE SINGLE USE PROMO" /><MealType code="1000021" text="Full board" /><Price amt="1899.30" /><Guests><Adult id="-153391725" first="" last=""><Price amt="949.65" /></Adult><Adult id="-153391726" first="" last=""><Price amt="949.65" /></Adult></Guests><CanxFees><Fee><Amount amt="1899.30" /></Fee></CanxFees></Room></Result><Result id="19618951-20"><Room><RoomType code="2141414" text="Room CAPACITY 9" /><MealType code="1000041" text="Room only" /><Price amt="115.10" /><Guests><Adult id="-153391727" first="" last=""><Price amt="57.55" /></Adult><Adult id="-153391728" first="" last=""><Price amt="57.55" /></Adult></Guests><CanxFees><Fee><Amount amt="115.10" /></Fee></CanxFees></Room></Result><Result id="19618951-21"><Room><RoomType code="1001784" text="Single Deluxe" /><MealType code="1000041" text="Room only" /><Price amt="172.70" /><Guests><Adult id="-153391729" first="" last=""><Price amt="86.35" /></Adult><Adult id="-153391730" first="" last=""><Price amt="86.35" /></Adult></Guests><CanxFees><Fee><Amount amt="172.70" /></Fee></CanxFees></Room></Result><Result id="19618951-22"><Room><RoomType code="2141414" text="Room CAPACITY 9" /><MealType code="1000018" text="Bed and breakfast" /><Price amt="230.20" /><Guests><Adult id="-153391731" first="" last=""><Price amt="115.10" /></Adult><Adult id="-153391732" first="" last=""><Price amt="115.10" /></Adult></Guests><CanxFees><Fee><Amount amt="230.20" /></Fee></CanxFees></Room></Result><Result id="19618951-23"><Room><RoomType code="1004525" text="Double Or Twin Standard" /><MealType code="1000041" text="Room only" /><Price amt="230.20" /><Guests><Adult id="-153391733" first="" last=""><Price amt="115.10" /></Adult><Adult id="-153391734" first="" last=""><Price amt="115.10" /></Adult></Guests><CanxFees><Fee><Amount amt="230.20" /></Fee></CanxFees></Room></Result><Result id="19618951-24"><Room><RoomType code="1800284" text="DOUBLE SINGLE USE STANDARD" /><MealType code="1000041" text="Room only" /><Price amt="287.80" /><Guests><Adult id="-153391735" first="" last=""><Price amt="143.90" /></Adult><Adult id="-153391736" first="" last=""><Price amt="143.90" /></Adult></Guests><CanxFees><Fee><Amount amt="287.80" /></Fee></CanxFees></Room></Result><Result id="19618951-25"><Room><RoomType code="2141414" text="Room CAPACITY 9" /><MealType code="1000019" text="Half board" /><Price amt="287.80" /><Guests><Adult id="-153391737" first="" last=""><Price amt="143.90" /></Adult><Adult id="-153391738" first="" last=""><Price amt="143.90" /></Adult></Guests><CanxFees><Fee><Amount amt="287.80" /></Fee></CanxFees></Room></Result><Result id="19618951-26"><Room><RoomType code="1001784" text="Single Deluxe" /><MealType code="1000018" text="Bed and breakfast" /><Price amt="287.80" /><Guests><Adult id="-153391739" first="" last=""><Price amt="143.90" /></Adult><Adult id="-153391740" first="" last=""><Price amt="143.90" /></Adult></Guests><CanxFees><Fee><Amount amt="287.80" /></Fee></CanxFees></Room></Result><Result id="19618951-27"><Room><RoomType code="2141414" text="Room CAPACITY 9" /><MealType code="1000021" text="Full board" /><Price amt="345.40" /><Guests><Adult id="-153391741" first="" last=""><Price amt="172.70" /></Adult><Adult id="-153391742" first="" last=""><Price amt="172.70" /></Adult></Guests><CanxFees><Fee><Amount amt="345.40" /></Fee></CanxFees></Room></Result><Result id="19618951-28"><Room><RoomType code="1001784" text="Single Deluxe" /><MealType code="1000019" text="Half board" /><Price amt="345.40" /><Guests><Adult id="-153391743" first="" last=""><Price amt="172.70" /></Adult><Adult id="-153391744" first="" last=""><Price amt="172.70" /></Adult></Guests><CanxFees><Fee><Amount amt="345.40" /></Fee></CanxFees></Room></Result><Result id="19618951-29"><Room><RoomType code="1002211" text="Triple Deluxe" /><MealType code="1000041" text="Room only" /><Price amt="345.40" /><Guests><Adult id="-153391745" first="" last=""><Price amt="172.70" /></Adult><Adult id="-153391746" first="" last=""><Price amt="172.70" /></Adult></Guests><CanxFees><Fee><Amount amt="345.40" /></Fee></CanxFees></Room></Result><Result id="19618951-30"><Room><RoomType code="1004525" text="Double Or Twin Standard" /><MealType code="1000018" text="Bed and breakfast" /><Price amt="345.40" /><Guests><Adult id="-153391747" first="" last=""><Price amt="172.70" /></Adult><Adult id="-153391748" first="" last=""><Price amt="172.70" /></Adult></Guests><CanxFees><Fee><Amount amt="345.40" /></Fee></CanxFees></Room></Result><Result id="19618951-31"><Room><RoomType code="1800284" text="DOUBLE SINGLE USE STANDARD" /><MealType code="1000018" text="Bed and breakfast" /><Price amt="402.90" /><Guests><Adult id="-153391749" first="" last=""><Price amt="201.45" /></Adult><Adult id="-153391750" first="" last=""><Price amt="201.45" /></Adult></Guests><CanxFees><Fee><Amount amt="402.90" /></Fee></CanxFees></Room></Result><Result id="19618951-32"><Room><RoomType code="1004527" text="Double Or Twin Deluxe" /><MealType code="1000041" text="Room only" /><Price amt="402.90" /><Guests><Adult id="-153391751" first="" last=""><Price amt="201.45" /></Adult><Adult id="-153391752" first="" last=""><Price amt="201.45" /></Adult></Guests><CanxFees><Fee><Amount amt="402.90" /></Fee></CanxFees></Room></Result><Result id="19618951-33"><Room><RoomType code="1001784" text="Single Deluxe" /><MealType code="1000021" text="Full board" /><Price amt="402.90" /><Guests><Adult id="-153391753" first="" last=""><Price amt="201.45" /></Adult><Adult id="-153391754" first="" last=""><Price amt="201.45" /></Adult></Guests><CanxFees><Fee><Amount amt="402.90" /></Fee></CanxFees></Room></Result><Result id="19618951-34"><Room><RoomType code="1004525" text="Double Or Twin Standard" /><MealType code="1000019" text="Half board" /><Price amt="402.90" /><Guests><Adult id="-153391755" first="" last=""><Price amt="201.45" /></Adult><Adult id="-153391756" first="" last=""><Price amt="201.45" /></Adult></Guests><CanxFees><Fee><Amount amt="402.90" /></Fee></CanxFees></Room></Result><Result id="19618951-35"><Room><RoomType code="1800284" text="DOUBLE SINGLE USE STANDARD" /><MealType code="1000019" text="Half board" /><Price amt="460.50" /><Guests><Adult id="-153391757" first="" last=""><Price amt="230.25" /></Adult><Adult id="-153391758" first="" last=""><Price amt="230.25" /></Adult></Guests><CanxFees><Fee><Amount amt="460.50" /></Fee></CanxFees></Room></Result><Result id="19618951-36"><Room><RoomType code="1002210" text="Double Deluxe" /><MealType code="1000041" text="Room only" /><Price amt="460.50" /><Guests><Adult id="-153391759" first="" last=""><Price amt="230.25" /></Adult><Adult id="-153391760" first="" last=""><Price amt="230.25" /></Adult></Guests><CanxFees><Fee><Amount amt="460.50" /></Fee></CanxFees></Room></Result><Result id="19618951-37"><Room><RoomType code="1002211" text="Triple Deluxe" /><MealType code="1000018" text="Bed and breakfast" /><Price amt="460.50" /><Guests><Adult id="-153391761" first="" last=""><Price amt="230.25" /></Adult><Adult id="-153391762" first="" last=""><Price amt="230.25" /></Adult></Guests><CanxFees><Fee><Amount amt="460.50" /></Fee></CanxFees></Room></Result><Result id="19618951-38"><Room><RoomType code="1004525" text="Double Or Twin Standard" /><MealType code="1000021" text="Full board" /><Price amt="460.50" /><Guests><Adult id="-153391763" first="" last=""><Price amt="230.25" /></Adult><Adult id="-153391764" first="" last=""><Price amt="230.25" /></Adult></Guests><CanxFees><Fee><Amount amt="460.50" /></Fee></CanxFees></Room></Result><Result id="19618951-39"><Room><RoomType code="1800284" text="DOUBLE SINGLE USE STANDARD" /><MealType code="1000021" text="Full board" /><Price amt="518.00" /><Guests><Adult id="-153391765" first="" last=""><Price amt="259.00" /></Adult><Adult id="-153391766" first="" last=""><Price amt="259.00" /></Adult></Guests><CanxFees><Fee><Amount amt="518.00" /></Fee></CanxFees></Room></Result><Result id="19618951-40"><Room><RoomType code="1004527" text="Double Or Twin Deluxe" /><MealType code="1000018" text="Bed and breakfast" /><Price amt="518.00" /><Guests><Adult id="-153391767" first="" last=""><Price amt="259.00" /></Adult><Adult id="-153391768" first="" last=""><Price amt="259.00" /></Adult></Guests><CanxFees><Fee><Amount amt="518.00" /></Fee></CanxFees></Room></Result><Result id="19618951-41"><Room><RoomType code="1800322" text="DOUBLE SINGLE USE DELUXE" /><MealType code="1000041" text="Room only" /><Price amt="518.00" /><Guests><Adult id="-153391769" first="" last=""><Price amt="259.00" /></Adult><Adult id="-153391770" first="" last=""><Price amt="259.00" /></Adult></Guests><CanxFees><Fee><Amount amt="518.00" /></Fee></CanxFees></Room></Result><Result id="19618951-42"><Room><RoomType code="1002211" text="Triple Deluxe" /><MealType code="1000019" text="Half board" /><Price amt="518.00" /><Guests><Adult id="-153391771" first="" last=""><Price amt="259.00" /></Adult><Adult id="-153391772" first="" last=""><Price amt="259.00" /></Adult></Guests><CanxFees><Fee><Amount amt="518.00" /></Fee></CanxFees></Room></Result><Result id="19618951-43"><Room><RoomType code="1002210" text="Double Deluxe" /><MealType code="1000018" text="Bed and breakfast" /><Price amt="575.60" /><Guests><Adult id="-153391773" first="" last=""><Price amt="287.80" /></Adult><Adult id="-153391774" first="" last=""><Price amt="287.80" /></Adult></Guests><CanxFees><Fee><Amount amt="575.60" /></Fee></CanxFees></Room></Result><Result id="19618951-44"><Room><RoomType code="1004527" text="Double Or Twin Deluxe" /><MealType code="1000019" text="Half board" /><Price amt="575.60" /><Guests><Adult id="-153391775" first="" last=""><Price amt="287.80" /></Adult><Adult id="-153391776" first="" last=""><Price amt="287.80" /></Adult></Guests><CanxFees><Fee><Amount amt="575.60" /></Fee></CanxFees></Room></Result><Result id="19618951-45"><Room><RoomType code="1002211" text="Triple Deluxe" /><MealType code="1000021" text="Full board" /><Price amt="575.60" /><Guests><Adult id="-153391777" first="" last=""><Price amt="287.80" /></Adult><Adult id="-153391778" first="" last=""><Price amt="287.80" /></Adult></Guests><CanxFees><Fee><Amount amt="575.60" /></Fee></CanxFees></Room></Result><Result id="19618951-46"><Room><RoomType code="1002210" text="Double Deluxe" /><MealType code="1000019" text="Half board" /><Price amt="633.10" /><Guests><Adult id="-153391779" first="" last=""><Price amt="316.55" /></Adult><Adult id="-153391780" first="" last=""><Price amt="316.55" /></Adult></Guests><CanxFees><Fee><Amount amt="633.10" /></Fee></CanxFees></Room></Result><Result id="19618951-47"><Room><RoomType code="2142445" text="Room WITH DOUBLE BED" /><MealType code="1000041" text="Room only" /><Price amt="633.10" /><Guests><Adult id="-153391781" first="" last=""><Price amt="316.55" /></Adult><Adult id="-153391782" first="" last=""><Price amt="316.55" /></Adult></Guests><CanxFees><Fee><Amount amt="633.10" /></Fee></CanxFees></Room></Result><Result id="19618951-48"><Room><RoomType code="1004527" text="Double Or Twin Deluxe" /><MealType code="1000021" text="Full board" /><Price amt="633.10" /><Guests><Adult id="-153391783" first="" last=""><Price amt="316.55" /></Adult><Adult id="-153391784" first="" last=""><Price amt="316.55" /></Adult></Guests><CanxFees><Fee><Amount amt="633.10" /></Fee></CanxFees></Room></Result><Result id="19618951-49"><Room><RoomType code="1800322" text="DOUBLE SINGLE USE DELUXE" /><MealType code="1000018" text="Bed and breakfast" /><Price amt="633.10" /><Guests><Adult id="-153391785" first="" last=""><Price amt="316.55" /></Adult><Adult id="-153391786" first="" last=""><Price amt="316.55" /></Adult></Guests><CanxFees><Fee><Amount amt="633.10" /></Fee></CanxFees></Room></Result><Result id="19618951-50"><Room><RoomType code="1002210" text="Double Deluxe" /><MealType code="1000021" text="Full board" /><Price amt="690.70" /><Guests><Adult id="-153391787" first="" last=""><Price amt="345.35" /></Adult><Adult id="-153391788" first="" last=""><Price amt="345.35" /></Adult></Guests><CanxFees><Fee><Amount amt="690.70" /></Fee></CanxFees></Room></Result><Result id="19618951-51"><Room><RoomType code="1800322" text="DOUBLE SINGLE USE DELUXE" /><MealType code="1000019" text="Half board" /><Price amt="690.70" /><Guests><Adult id="-153391789" first="" last=""><Price amt="345.35" /></Adult><Adult id="-153391790" first="" last=""><Price amt="345.35" /></Adult></Guests><CanxFees><Fee><Amount amt="690.70" /></Fee></CanxFees></Room></Result><Result id="19618951-52"><Room><RoomType code="2142445" text="Room WITH DOUBLE BED" /><MealType code="1000018" text="Bed and breakfast" /><Price amt="748.20" /><Guests><Adult id="-153391791" first="" last=""><Price amt="374.10" /></Adult><Adult id="-153391792" first="" last=""><Price amt="374.10" /></Adult></Guests><CanxFees><Fee><Amount amt="748.20" /></Fee></CanxFees></Room></Result><Result id="19618951-53"><Room><RoomType code="1002066" text="Quadruple Standard" /><MealType code="1000041" text="Room only" /><Price amt="748.20" /><Guests><Adult id="-153391793" first="" last=""><Price amt="374.10" /></Adult><Adult id="-153391794" first="" last=""><Price amt="374.10" /></Adult></Guests><CanxFees><Fee><Amount amt="748.20" /></Fee></CanxFees></Room></Result><Result id="19618951-54"><Room><RoomType code="1800322" text="DOUBLE SINGLE USE DELUXE" /><MealType code="1000021" text="Full board" /><Price amt="748.20" /><Guests><Adult id="-153391795" first="" last=""><Price amt="374.10" /></Adult><Adult id="-153391796" first="" last=""><Price amt="374.10" /></Adult></Guests><CanxFees><Fee><Amount amt="748.20" /></Fee></CanxFees></Room></Result><Result id="19618951-55"><Room><RoomType code="2142445" text="Room WITH DOUBLE BED" /><MealType code="1000019" text="Half board" /><Price amt="805.80" /><Guests><Adult id="-153391797" first="" last=""><Price amt="402.90" /></Adult><Adult id="-153391798" first="" last=""><Price amt="402.90" /></Adult></Guests><CanxFees><Fee><Amount amt="805.80" /></Fee></CanxFees></Room></Result><Result id="19618951-56"><Room><RoomType code="2142445" text="Room WITH DOUBLE BED" /><MealType code="1000021" text="Full board" /><Price amt="863.30" /><Guests><Adult id="-153391799" first="" last=""><Price amt="431.65" /></Adult><Adult id="-153391800" first="" last=""><Price amt="431.65" /></Adult></Guests><CanxFees><Fee><Amount amt="863.30" /></Fee></CanxFees></Room></Result><Result id="19618951-57"><Room><RoomType code="1002066" text="Quadruple Standard" /><MealType code="1000018" text="Bed and breakfast" /><Price amt="863.30" /><Guests><Adult id="-153391801" first="" last=""><Price amt="431.65" /></Adult><Adult id="-153391802" first="" last=""><Price amt="431.65" /></Adult></Guests><CanxFees><Fee><Amount amt="863.30" /></Fee></CanxFees></Room></Result><Result id="19618951-58"><Room><RoomType code="2141409" text="Room CAPACITY 5" /><MealType code="1000041" text="Room only" /><Price amt="920.90" /><Guests><Adult id="-153391803" first="" last=""><Price amt="460.45" /></Adult><Adult id="-153391804" first="" last=""><Price amt="460.45" /></Adult></Guests><CanxFees><Fee><Amount amt="920.90" /></Fee></CanxFees></Room></Result><Result id="19618951-59"><Room><RoomType code="1002066" text="Quadruple Standard" /><MealType code="1000019" text="Half board" /><Price amt="920.90" /><Guests><Adult id="-153391805" first="" last=""><Price amt="460.45" /></Adult><Adult id="-153391806" first="" last=""><Price amt="460.45" /></Adult></Guests><CanxFees><Fee><Amount amt="920.90" /></Fee></CanxFees></Room></Result><Result id="19618951-60"><Room><RoomType code="1002066" text="Quadruple Standard" /><MealType code="1000021" text="Full board" /><Price amt="978.40" /><Guests><Adult id="-153391807" first="" last=""><Price amt="489.20" /></Adult><Adult id="-153391808" first="" last=""><Price amt="489.20" /></Adult></Guests><CanxFees><Fee><Amount amt="978.40" /></Fee></CanxFees></Room></Result><Result id="19618951-61"><Room><RoomType code="1002008" text="Twin Standard" /><MealType code="1000019" text="Half board" /><Price amt="1036.00" /><Guests><Adult id="-153391809" first="" last=""><Price amt="518.00" /></Adult><Adult id="-153391810" first="" last=""><Price amt="518.00" /></Adult></Guests><CanxFees><Fee><Amount amt="1036.00" /></Fee></CanxFees></Room></Result><Result id="19618951-62"><Room><RoomType code="2141409" text="Room CAPACITY 5" /><MealType code="1000018" text="Bed and breakfast" /><Price amt="1036.00" /><Guests><Adult id="-153391811" first="" last=""><Price amt="518.00" /></Adult><Adult id="-153391812" first="" last=""><Price amt="518.00" /></Adult></Guests><CanxFees><Fee><Amount amt="1036.00" /></Fee></CanxFees></Room></Result><Result id="19618951-63"><Room><RoomType code="1002065" text="Triple Standard" /><MealType code="1000041" text="Room only" /><Price amt="1036.00" /><Guests><Adult id="-153391813" first="" last=""><Price amt="518.00" /></Adult><Adult id="-153391814" first="" last=""><Price amt="518.00" /></Adult></Guests><CanxFees><Fee><Amount amt="1036.00" /></Fee></CanxFees></Room></Result><Result id="19618951-64"><Room><RoomType code="1002008" text="Twin Standard" /><MealType code="1000021" text="Full board" /><Price amt="1093.50" /><Guests><Adult id="-153391815" first="" last=""><Price amt="546.75" /></Adult><Adult id="-153391816" first="" last=""><Price amt="546.75" /></Adult></Guests><CanxFees><Fee><Amount amt="1093.50" /></Fee></CanxFees></Room></Result><Result id="19618951-65"><Room><RoomType code="2141409" text="Room CAPACITY 5" /><MealType code="1000019" text="Half board" /><Price amt="1093.50" /><Guests><Adult id="-153391817" first="" last=""><Price amt="546.75" /></Adult><Adult id="-153391818" first="" last=""><Price amt="546.75" /></Adult></Guests><CanxFees><Fee><Amount amt="1093.50" /></Fee></CanxFees></Room></Result><Result id="19618951-66"><Room><RoomType code="2141411" text="Room CAPACITY 6" /><MealType code="1000041" text="Room only" /><Price amt="1093.50" /><Guests><Adult id="-153391819" first="" last=""><Price amt="546.75" /></Adult><Adult id="-153391820" first="" last=""><Price amt="546.75" /></Adult></Guests><CanxFees><Fee><Amount amt="1093.50" /></Fee></CanxFees></Room></Result><Result id="19618951-67"><Room><RoomType code="2141409" text="Room CAPACITY 5" /><MealType code="1000021" text="Full board" /><Price amt="1151.10" /><Guests><Adult id="-153391821" first="" last=""><Price amt="575.55" /></Adult><Adult id="-153391822" first="" last=""><Price amt="575.55" /></Adult></Guests><CanxFees><Fee><Amount amt="1151.10" /></Fee></CanxFees></Room></Result><Result id="19618951-68"><Room><RoomType code="2141412" text="Room CAPACITY 7" /><MealType code="1000041" text="Room only" /><Price amt="1151.10" /><Guests><Adult id="-153391823" first="" last=""><Price amt="575.55" /></Adult><Adult id="-153391824" first="" last=""><Price amt="575.55" /></Adult></Guests><CanxFees><Fee><Amount amt="1151.10" /></Fee></CanxFees></Room></Result><Result id="19618951-69"><Room><RoomType code="1002065" text="Triple Standard" /><MealType code="1000018" text="Bed and breakfast" /><Price amt="1151.10" /><Guests><Adult id="-153391825" first="" last=""><Price amt="575.55" /></Adult><Adult id="-153391826" first="" last=""><Price amt="575.55" /></Adult></Guests><CanxFees><Fee><Amount amt="1151.10" /></Fee></CanxFees></Room></Result><Result id="19618951-70"><Room><RoomType code="1002065" text="Triple Standard" /><MealType code="1000019" text="Half board" /><Price amt="1208.60" /><Guests><Adult id="-153391827" first="" last=""><Price amt="604.30" /></Adult><Adult id="-153391828" first="" last=""><Price amt="604.30" /></Adult></Guests><CanxFees><Fee><Amount amt="1208.60" /></Fee></CanxFees></Room></Result><Result id="19618951-71"><Room><RoomType code="2141411" text="Room CAPACITY 6" /><MealType code="1000018" text="Bed and breakfast" /><Price amt="1208.60" /><Guests><Adult id="-153391829" first="" last=""><Price amt="604.30" /></Adult><Adult id="-153391830" first="" last=""><Price amt="604.30" /></Adult></Guests><CanxFees><Fee><Amount amt="1208.60" /></Fee></CanxFees></Room></Result><Result id="19618951-72"><Room><RoomType code="2142689" text="Bed in dormitory STANDARD" /><MealType code="1000041" text="Room only" /><Price amt="1208.60" /><Guests><Adult id="-153391831" first="" last=""><Price amt="604.30" /></Adult><Adult id="-153391832" first="" last=""><Price amt="604.30" /></Adult></Guests><CanxFees><Fee><Amount amt="1208.60" /></Fee></CanxFees></Room></Result><Result id="19618951-73"><Room><RoomType code="2141412" text="Room CAPACITY 7" /><MealType code="1000018" text="Bed and breakfast" /><Price amt="1266.20" /><Guests><Adult id="-153391833" first="" last=""><Price amt="633.10" /></Adult><Adult id="-153391834" first="" last=""><Price amt="633.10" /></Adult></Guests><CanxFees><Fee><Amount amt="1266.20" /></Fee></CanxFees></Room></Result><Result id="19618951-74"><Room><RoomType code="1002065" text="Triple Standard" /><MealType code="1000021" text="Full board" /><Price amt="1266.20" /><Guests><Adult id="-153391835" first="" last=""><Price amt="633.10" /></Adult><Adult id="-153391836" first="" last=""><Price amt="633.10" /></Adult></Guests><CanxFees><Fee><Amount amt="1266.20" /></Fee></CanxFees></Room></Result><Result id="19618951-75"><Room><RoomType code="2141411" text="Room CAPACITY 6" /><MealType code="1000019" text="Half board" /><Price amt="1266.20" /><Guests><Adult id="-153391837" first="" last=""><Price amt="633.10" /></Adult><Adult id="-153391838" first="" last=""><Price amt="633.10" /></Adult></Guests><CanxFees><Fee><Amount amt="1266.20" /></Fee></CanxFees></Room></Result><Result id="19618951-76"><Room><RoomType code="2141412" text="Room CAPACITY 7" /><MealType code="1000019" text="Half board" /><Price amt="1323.70" /><Guests><Adult id="-153391839" first="" last=""><Price amt="661.85" /></Adult><Adult id="-153391840" first="" last=""><Price amt="661.85" /></Adult></Guests><CanxFees><Fee><Amount amt="1323.70" /></Fee></CanxFees></Room></Result><Result id="19618951-77"><Room><RoomType code="2141411" text="Room CAPACITY 6" /><MealType code="1000021" text="Full board" /><Price amt="1323.70" /><Guests><Adult id="-153391841" first="" last=""><Price amt="661.85" /></Adult><Adult id="-153391842" first="" last=""><Price amt="661.85" /></Adult></Guests><CanxFees><Fee><Amount amt="1323.70" /></Fee></CanxFees></Room></Result><Result id="19618951-78"><Room><RoomType code="2142689" text="Bed in dormitory STANDARD" /><MealType code="1000018" text="Bed and breakfast" /><Price amt="1323.70" /><Guests><Adult id="-153391843" first="" last=""><Price amt="661.85" /></Adult><Adult id="-153391844" first="" last=""><Price amt="661.85" /></Adult></Guests><CanxFees><Fee><Amount amt="1323.70" /></Fee></CanxFees></Room></Result><Result id="19618951-79"><Room><RoomType code="2145161" text="Bed in dormitory BUNK BED" /><MealType code="1000041" text="Room only" /><Price amt="1381.30" /><Guests><Adult id="-153391845" first="" last=""><Price amt="690.65" /></Adult><Adult id="-153391846" first="" last=""><Price amt="690.65" /></Adult></Guests><CanxFees><Fee><Amount amt="1381.30" /></Fee></CanxFees></Room></Result><Result id="19618951-80"><Room><RoomType code="2141412" text="Room CAPACITY 7" /><MealType code="1000021" text="Full board" /><Price amt="1381.30" /><Guests><Adult id="-153391847" first="" last=""><Price amt="690.65" /></Adult><Adult id="-153391848" first="" last=""><Price amt="690.65" /></Adult></Guests><CanxFees><Fee><Amount amt="1381.30" /></Fee></CanxFees></Room></Result><Result id="19618951-81"><Room><RoomType code="2142689" text="Bed in dormitory STANDARD" /><MealType code="1000019" text="Half board" /><Price amt="1381.30" /><Guests><Adult id="-153391849" first="" last=""><Price amt="690.65" /></Adult><Adult id="-153391850" first="" last=""><Price amt="690.65" /></Adult></Guests><CanxFees><Fee><Amount amt="1381.30" /></Fee></CanxFees></Room></Result><Result id="19618951-82"><Room><RoomType code="2142689" text="Bed in dormitory STANDARD" /><MealType code="1000021" text="Full board" /><Price amt="1438.80" /><Guests><Adult id="-153391851" first="" last=""><Price amt="719.40" /></Adult><Adult id="-153391852" first="" last=""><Price amt="719.40" /></Adult></Guests><CanxFees><Fee><Amount amt="1438.80" /></Fee></CanxFees></Room></Result><Result id="19618951-83"><Room><RoomType code="2145161" text="Bed in dormitory BUNK BED" /><MealType code="1000018" text="Bed and breakfast" /><Price amt="1496.40" /><Guests><Adult id="-153391853" first="" last=""><Price amt="748.20" /></Adult><Adult id="-153391854" first="" last=""><Price amt="748.20" /></Adult></Guests><CanxFees><Fee><Amount amt="1496.40" /></Fee></CanxFees></Room></Result><Result id="19618951-84"><Room><RoomType code="1971263" text="Room Standard" /><MealType code="1000041" text="Room only" /><Price amt="1496.40" /><Guests><Adult id="-153391855" first="" last=""><Price amt="748.20" /></Adult><Adult id="-153391856" first="" last=""><Price amt="748.20" /></Adult></Guests><CanxFees><Fee><Amount amt="1496.40" /></Fee></CanxFees></Room></Result><Result id="19618951-85"><Room><RoomType code="2145161" text="Bed in dormitory BUNK BED" /><MealType code="1000019" text="Half board" /><Price amt="1553.90" /><Guests><Adult id="-153391857" first="" last=""><Price amt="776.95" /></Adult><Adult id="-153391858" first="" last=""><Price amt="776.95" /></Adult></Guests><CanxFees><Fee><Amount amt="1553.90" /></Fee></CanxFees></Room></Result><Result id="19618951-86"><Room><RoomType code="2145161" text="Bed in dormitory BUNK BED" /><MealType code="1000021" text="Full board" /><Price amt="1611.50" /><Guests><Adult id="-153391859" first="" last=""><Price amt="805.75" /></Adult><Adult id="-153391860" first="" last=""><Price amt="805.75" /></Adult></Guests><CanxFees><Fee><Amount amt="1611.50" /></Fee></CanxFees></Room></Result><Result id="19618951-87"><Room><RoomType code="2097911" text="TWIN CAPACITY 1" /><MealType code="1000041" text="Room only" /><Price amt="1611.50" /><Guests><Adult id="-153391861" first="" last=""><Price amt="805.75" /></Adult><Adult id="-153391862" first="" last=""><Price amt="805.75" /></Adult></Guests><CanxFees><Fee><Amount amt="1611.50" /></Fee></CanxFees></Room></Result><Result id="19618951-88"><Room><RoomType code="1971263" text="Room Standard" /><MealType code="1000018" text="Bed and breakfast" /><Price amt="1611.50" /><Guests><Adult id="-153391863" first="" last=""><Price amt="805.75" /></Adult><Adult id="-153391864" first="" last=""><Price amt="805.75" /></Adult></Guests><CanxFees><Fee><Amount amt="1611.50" /></Fee></CanxFees></Room></Result><Result id="19618951-89"><Room><RoomType code="2141413" text="Room CAPACITY 8" /><MealType code="1000041" text="Room only" /><Price amt="1669.00" /><Guests><Adult id="-153391865" first="" last=""><Price amt="834.50" /></Adult><Adult id="-153391866" first="" last=""><Price amt="834.50" /></Adult></Guests><CanxFees><Fee><Amount amt="1669.00" /></Fee></CanxFees></Room></Result><Result id="19618951-90"><Room><RoomType code="1971263" text="Room Standard" /><MealType code="1000019" text="Half board" /><Price amt="1669.00" /><Guests><Adult id="-153391867" first="" last=""><Price amt="834.50" /></Adult><Adult id="-153391868" first="" last=""><Price amt="834.50" /></Adult></Guests><CanxFees><Fee><Amount amt="1669.00" /></Fee></CanxFees></Room></Result><Result id="19618951-91"><Room><RoomType code="2097911" text="TWIN CAPACITY 1" /><MealType code="1000018" text="Bed and breakfast" /><Price amt="1726.60" /><Guests><Adult id="-153391869" first="" last=""><Price amt="863.30" /></Adult><Adult id="-153391870" first="" last=""><Price amt="863.30" /></Adult></Guests><CanxFees><Fee><Amount amt="1726.60" /></Fee></CanxFees></Room></Result><Result id="19618951-92"><Room><RoomType code="1971263" text="Room Standard" /><MealType code="1000021" text="Full board" /><Price amt="1726.60" /><Guests><Adult id="-153391871" first="" last=""><Price amt="863.30" /></Adult><Adult id="-153391872" first="" last=""><Price amt="863.30" /></Adult></Guests><CanxFees><Fee><Amount amt="1726.60" /></Fee></CanxFees></Room></Result><Result id="19618951-93"><Room><RoomType code="2097911" text="TWIN CAPACITY 1" /><MealType code="1000019" text="Half board" /><Price amt="1784.10" /><Guests><Adult id="-153391873" first="" last=""><Price amt="892.05" /></Adult><Adult id="-153391874" first="" last=""><Price amt="892.05" /></Adult></Guests><CanxFees><Fee><Amount amt="1784.10" /></Fee></CanxFees></Room></Result><Result id="19618951-94"><Room><RoomType code="2141413" text="Room CAPACITY 8" /><MealType code="1000018" text="Bed and breakfast" /><Price amt="1784.10" /><Guests><Adult id="-153391875" first="" last=""><Price amt="892.05" /></Adult><Adult id="-153391876" first="" last=""><Price amt="892.05" /></Adult></Guests><CanxFees><Fee><Amount amt="1784.10" /></Fee></CanxFees></Room></Result><Result id="19618951-95"><Room><RoomType code="2097911" text="TWIN CAPACITY 1" /><MealType code="1000021" text="Full board" /><Price amt="1841.70" /><Guests><Adult id="-153391877" first="" last=""><Price amt="920.85" /></Adult><Adult id="-153391878" first="" last=""><Price amt="920.85" /></Adult></Guests><CanxFees><Fee><Amount amt="1841.70" /></Fee></CanxFees></Room></Result><Result id="19618951-96"><Room><RoomType code="2141413" text="Room CAPACITY 8" /><MealType code="1000019" text="Half board" /><Price amt="1841.70" /><Guests><Adult id="-153391879" first="" last=""><Price amt="920.85" /></Adult><Adult id="-153391880" first="" last=""><Price amt="920.85" /></Adult></Guests><CanxFees><Fee><Amount amt="1841.70" /></Fee></CanxFees></Room></Result><Result id="19618951-97"><Room><RoomType code="2145162" text="Bed in dormitory MALE ROOM" /><MealType code="1000041" text="Room only" /><Price amt="1899.30" /><Guests><Adult id="-153391881" first="" last=""><Price amt="949.65" /></Adult><Adult id="-153391882" first="" last=""><Price amt="949.65" /></Adult></Guests><CanxFees><Fee><Amount amt="1899.30" /></Fee></CanxFees></Room></Result><Result id="19618951-98"><Room><RoomType code="2141413" text="Room CAPACITY 8" /><MealType code="1000021" text="Full board" /><Price amt="1899.30" /><Guests><Adult id="-153391883" first="" last=""><Price amt="949.65" /></Adult><Adult id="-153391884" first="" last=""><Price amt="949.65" /></Adult></Guests><CanxFees><Fee><Amount amt="1899.30" /></Fee></CanxFees></Room></Result><Result id="19618951-99"><Room><RoomType code="2145162" text="Bed in dormitory MALE ROOM" /><MealType code="1000018" text="Bed and breakfast" /><Price amt="2014.40" /><Guests><Adult id="-153391885" first="" last=""><Price amt="1007.20" /></Adult><Adult id="-153391886" first="" last=""><Price amt="1007.20" /></Adult></Guests><CanxFees><Fee><Amount amt="2014.40" /></Fee></CanxFees></Room></Result><Result id="19618951-100"><Room><RoomType code="2145162" text="Bed in dormitory MALE ROOM" /><MealType code="1000019" text="Half board" /><Price amt="2071.90" /><Guests><Adult id="-153391887" first="" last=""><Price amt="1035.95" /></Adult><Adult id="-153391888" first="" last=""><Price amt="1035.95" /></Adult></Guests><CanxFees><Fee><Amount amt="2071.90" /></Fee></CanxFees></Room></Result><Result id="19618951-101"><Room><RoomType code="2145163" text="Bed in dormitory FEMALE ROOM" /><MealType code="1000041" text="Room only" /><Price amt="2071.90" /><Guests><Adult id="-153391889" first="" last=""><Price amt="1035.95" /></Adult><Adult id="-153391890" first="" last=""><Price amt="1035.95" /></Adult></Guests><CanxFees><Fee><Amount amt="2071.90" /></Fee></CanxFees></Room></Result><Result id="19618951-102"><Room><RoomType code="2145162" text="Bed in dormitory MALE ROOM" /><MealType code="1000021" text="Full board" /><Price amt="2129.50" /><Guests><Adult id="-153391891" first="" last=""><Price amt="1064.75" /></Adult><Adult id="-153391892" first="" last=""><Price amt="1064.75" /></Adult></Guests><CanxFees><Fee><Amount amt="2129.50" /></Fee></CanxFees></Room></Result><Result id="19618951-103"><Room><RoomType code="2145163" text="Bed in dormitory FEMALE ROOM" /><MealType code="1000018" text="Bed and breakfast" /><Price amt="2187.00" /><Guests><Adult id="-153391893" first="" last=""><Price amt="1093.50" /></Adult><Adult id="-153391894" first="" last=""><Price amt="1093.50" /></Adult></Guests><CanxFees><Fee><Amount amt="2187.00" /></Fee></CanxFees></Room></Result><Result id="19618951-104"><Room><RoomType code="2145163" text="Bed in dormitory FEMALE ROOM" /><MealType code="1000019" text="Half board" /><Price amt="2244.60" /><Guests><Adult id="-153391895" first="" last=""><Price amt="1122.30" /></Adult><Adult id="-153391896" first="" last=""><Price amt="1122.30" /></Adult></Guests><CanxFees><Fee><Amount amt="2244.60" /></Fee></CanxFees></Room></Result><Result id="19618951-105"><Room><RoomType code="2145163" text="Bed in dormitory FEMALE ROOM" /><MealType code="1000021" text="Full board" /><Price amt="2302.10" /><Guests><Adult id="-153391897" first="" last=""><Price amt="1151.05" /></Adult><Adult id="-153391898" first="" last=""><Price amt="1151.05" /></Adult></Guests><CanxFees><Fee><Amount amt="2302.10" /></Fee></CanxFees></Room></Result><Result id="19618951-106"><Room><RoomType code="1002196" text="Double Standard" /><MealType code="1000041" text="Room only" /><Price amt="119.70" /><Guests><Adult id="-153391919" first="" last=""><Price amt="59.85" /></Adult><Adult id="-153391920" first="" last=""><Price amt="59.85" /></Adult></Guests><CanxFees><Fee><Amount amt="119.70" /></Fee></CanxFees></Room></Result><Result id="19618951-107"><Room><RoomType code="1002008" text="Twin Standard" /><MealType code="1000041" text="Room only" /><Price amt="119.70" /><Guests><Adult id="-153391921" first="" last=""><Price amt="59.85" /></Adult><Adult id="-153391922" first="" last=""><Price amt="59.85" /></Adult></Guests><CanxFees><Fee><Amount amt="119.70" /></Fee></CanxFees></Room></Result><Result id="19618951-108"><Room><RoomType code="1002196" text="Double Standard" /><MealType code="1000041" text="Room only" /><Price amt="126.00" /><Guests><Adult id="-153391923" first="" last=""><Price amt="63.00" /></Adult><Adult id="-153391924" first="" last=""><Price amt="63.00" /></Adult></Guests><CanxFees><Fee><Amount amt="126.00" /></Fee></CanxFees></Room></Result><Result id="19618951-109"><Room><RoomType code="1002008" text="Twin Standard" /><MealType code="1000041" text="Room only" /><Price amt="126.00" /><Guests><Adult id="-153391925" first="" last=""><Price amt="63.00" /></Adult><Adult id="-153391926" first="" last=""><Price amt="63.00" /></Adult></Guests><CanxFees><Fee><Amount amt="126.00" /></Fee></CanxFees></Room></Result><Result id="19618951-110"><Room><RoomType code="1002196" text="Double Standard" /><MealType code="1000018" text="Bed and breakfast" /><Price amt="137.60" /><Guests><Adult id="-153391927" first="" last=""><Price amt="68.80" /></Adult><Adult id="-153391928" first="" last=""><Price amt="68.80" /></Adult></Guests><CanxFees><Fee><Amount amt="137.60" /></Fee></CanxFees></Room></Result><Result id="19618951-111"><Room><RoomType code="1002008" text="Twin Standard" /><MealType code="1000018" text="Bed and breakfast" /><Price amt="137.60" /><Guests><Adult id="-153391929" first="" last=""><Price amt="68.80" /></Adult><Adult id="-153391930" first="" last=""><Price amt="68.80" /></Adult></Guests><CanxFees><Fee><Amount amt="137.60" /></Fee></CanxFees></Room></Result><Result id="19618951-112"><Room><RoomType code="1002196" text="Double Standard" /><MealType code="1000018" text="Bed and breakfast" /><Price amt="144.80" /><Guests><Adult id="-153391931" first="" last=""><Price amt="72.40" /></Adult><Adult id="-153391932" first="" last=""><Price amt="72.40" /></Adult></Guests><CanxFees><Fee><Amount amt="144.80" /></Fee></CanxFees></Room></Result><Result id="19618951-113"><Room><RoomType code="1002008" text="Twin Standard" /><MealType code="1000018" text="Bed and breakfast" /><Price amt="144.80" /><Guests><Adult id="-153391933" first="" last=""><Price amt="72.40" /></Adult><Adult id="-153391934" first="" last=""><Price amt="72.40" /></Adult></Guests><CanxFees><Fee><Amount amt="144.80" /></Fee></CanxFees></Room></Result></HotelAvailability></AvailabilitySearchResult>